{"schemaVersion":1,"lineId":"IDFM:C01863","routeIds":["IDFM:C01863"],"labels":["TER","TER Hauts-de-France"],"routeTypes":["2"],"patterns":[{"id":"781460276cc9fe4c","shapeId":"IDFM:shp_2_152","direction":"1","stopIds":["IDFM:71410","IDFM:69254","IDFM:411406","IDFM:411391","IDFM:411397"],"shapeDirection":"forward","projections":[{"stopId":"IDFM:71410","shapePointIndex":0,"segmentProgress":0,"distanceAlongMeters":0,"errorMeters":91.5628988068051,"coordinate":{"lon":2.357134,"lat":48.881462}},{"stopId":"IDFM:69254","shapePointIndex":191,"segmentProgress":0.061946518907033385,"distanceAlongMeters":34228.14996818094,"errorMeters":19.192934985236274,"coordinate":{"lon":2.699278635875679,"lat":49.03239194526137}},{"stopId":"IDFM:411406","shapePointIndex":204,"segmentProgress":0.9657511321537493,"distanceAlongMeters":42084.14894508382,"errorMeters":11.961551303714204,"coordinate":{"lon":2.7449026698268857,"lat":49.096219588098194}},{"stopId":"IDFM:411391","shapePointIndex":207,"segmentProgress":0.99253800434156,"distanceAlongMeters":48370.310951305706,"errorMeters":17.519812572464186,"coordinate":{"lon":2.7941179093638717,"lat":49.1426012663361}},{"stopId":"IDFM:411397","shapePointIndex":260,"segmentProgress":1,"distanceAlongMeters":60627.67755586481,"errorMeters":83.65842200753443,"coordinate":{"lon":2.88649,"lat":49.231106}}]},{"id":"0b6b6e6556c6d0b1","shapeId":"IDFM:shp_2_152","direction":"1","stopIds":["IDFM:71410","IDFM:69254","IDFM:411397"],"shapeDirection":"forward","projections":[{"stopId":"IDFM:71410","shapePointIndex":0,"segmentProgress":0,"distanceAlongMeters":0,"errorMeters":91.5628988068051,"coordinate":{"lon":2.357134,"lat":48.881462}},{"stopId":"IDFM:69254","shapePointIndex":191,"segmentProgress":0.061946518907033385,"distanceAlongMeters":34228.14996818094,"errorMeters":19.192934985236274,"coordinate":{"lon":2.699278635875679,"lat":49.03239194526137}},{"stopId":"IDFM:411397","shapePointIndex":260,"segmentProgress":1,"distanceAlongMeters":60627.67755586481,"errorMeters":83.65842200753443,"coordinate":{"lon":2.88649,"lat":49.231106}}]},{"id":"99b95685b6bdf038","shapeId":"IDFM:shp_2_68","direction":"0","stopIds":["IDFM:411397","IDFM:69254","IDFM:71410"],"shapeDirection":"forward","projections":[{"stopId":"IDFM:411397","shapePointIndex":0,"segmentProgress":0,"distanceAlongMeters":0,"errorMeters":83.94166610837166,"coordinate":{"lon":2.886496,"lat":49.231071}},{"stopId":"IDFM:69254","shapePointIndex":66,"segmentProgress":0.9647866634572689,"distanceAlongMeters":26395.879127989607,"errorMeters":22.942895826041614,"coordinate":{"lon":2.69932428688565,"lat":49.03237648737077}},{"stopId":"IDFM:71410","shapePointIndex":281,"segmentProgress":1,"distanceAlongMeters":60620.47971101903,"errorMeters":108.60567433335284,"coordinate":{"lon":2.357473,"lat":48.881393}}]},{"id":"ed891b57a249d8f5","shapeId":"IDFM:shp_2_264","direction":"1","stopIds":["IDFM:69065","IDFM:69254","IDFM:411397"],"shapeDirection":"forward","projections":[{"stopId":"IDFM:69065","shapePointIndex":0,"segmentProgress":0.009747333134822797,"distanceAlongMeters":3.7354312171158366,"errorMeters":32.22877163120947,"coordinate":{"lon":2.6423183340826135,"lat":48.97594925136484}},{"stopId":"IDFM:69254","shapePointIndex":23,"segmentProgress":0.061946518907033385,"distanceAlongMeters":7613.620733077315,"errorMeters":19.192934985236274,"coordinate":{"lon":2.699278635875679,"lat":49.03239194526137}},{"stopId":"IDFM:411397","shapePointIndex":92,"segmentProgress":1,"distanceAlongMeters":34013.148320761204,"errorMeters":83.65842200753443,"coordinate":{"lon":2.88649,"lat":49.231106}}]},{"id":"440a24826e5d36d6","shapeId":"IDFM:shp_2_67","direction":"0","stopIds":["IDFM:411397","IDFM:69254","IDFM:69065"],"shapeDirection":"forward","projections":[{"stopId":"IDFM:411397","shapePointIndex":0,"segmentProgress":0,"distanceAlongMeters":0,"errorMeters":83.94166610837166,"coordinate":{"lon":2.886496,"lat":49.231071}},{"stopId":"IDFM:69254","shapePointIndex":66,"segmentProgress":0.9647866634572689,"distanceAlongMeters":26395.879127989607,"errorMeters":22.942895826041614,"coordinate":{"lon":2.69932428688565,"lat":49.03237648737077}},{"stopId":"IDFM:69065","shapePointIndex":94,"segmentProgress":0.9902526668651772,"distanceAlongMeters":34006.915332245386,"errorMeters":32.22877163120947,"coordinate":{"lon":2.6423183340826135,"lat":48.97594925136484}}]},{"id":"c53f2cb3aca9640c","shapeId":"IDFM:shp_2_206","direction":"1","stopIds":["IDFM:71410","IDFM:411397"],"shapeDirection":"forward","projections":[{"stopId":"IDFM:71410","shapePointIndex":0,"segmentProgress":0,"distanceAlongMeters":0,"errorMeters":91.5628988068051,"coordinate":{"lon":2.357134,"lat":48.881462}},{"stopId":"IDFM:411397","shapePointIndex":743,"segmentProgress":1,"distanceAlongMeters":98669.33183959409,"errorMeters":83.65842200753443,"coordinate":{"lon":2.88649,"lat":49.231106}}]},{"id":"b45408ceed04d5c9","shapeId":"IDFM:shp_2_70","direction":"0","stopIds":["IDFM:411397","IDFM:71410"],"shapeDirection":"forward","projections":[{"stopId":"IDFM:411397","shapePointIndex":0,"segmentProgress":0,"distanceAlongMeters":0,"errorMeters":83.94166610837166,"coordinate":{"lon":2.886496,"lat":49.231071}},{"stopId":"IDFM:71410","shapePointIndex":769,"segmentProgress":1,"distanceAlongMeters":98628.24860938937,"errorMeters":108.60567433335284,"coordinate":{"lon":2.357473,"lat":48.881393}}]}],"shapes":{"IDFM:shp_2_152":[{"lat":48.881462,"lon":2.357134},{"lat":48.882149,"lon":2.35744},{"lat":48.882404,"lon":2.357531},{"lat":48.882759,"lon":2.35763},{"lat":48.883118,"lon":2.357696},{"lat":48.883362,"lon":2.357724},{"lat":48.884266,"lon":2.357777},{"lat":48.884686,"lon":2.357885},{"lat":48.885208,"lon":2.357942},{"lat":48.886402,"lon":2.357929},{"lat":48.887524,"lon":2.357854},{"lat":48.88834,"lon":2.357781},{"lat":48.889816,"lon":2.357557},{"lat":48.890144,"lon":2.357486},{"lat":48.890472,"lon":2.357395},{"lat":48.890755,"lon":2.357292},{"lat":48.891155,"lon":2.357122},{"lat":48.894276,"lon":2.35563},{"lat":48.894806,"lon":2.355417},{"lat":48.896339,"lon":2.354898},{"lat":48.896965,"lon":2.35472},{"lat":48.897404,"lon":2.354626},{"lat":48.897556,"lon":2.354602},{"lat":48.897942,"lon":2.354564},{"lat":48.899231,"lon":2.354511},{"lat":48.899654,"lon":2.354477},{"lat":48.899857,"lon":2.35445},{"lat":48.90012,"lon":2.354402},{"lat":48.902699,"lon":2.353812},{"lat":48.90345,"lon":2.353653},{"lat":48.903824,"lon":2.353565},{"lat":48.904243,"lon":2.353436},{"lat":48.904778,"lon":2.353224},{"lat":48.905396,"lon":2.353019},{"lat":48.905724,"lon":2.352944},{"lat":48.906128,"lon":2.35287},{"lat":48.907642,"lon":2.352561},{"lat":48.908234,"lon":2.352433},{"lat":48.908489,"lon":2.352406},{"lat":48.909443,"lon":2.352351},{"lat":48.91011,"lon":2.352321},{"lat":48.91029,"lon":2.352321},{"lat":48.910641,"lon":2.352343},{"lat":48.910877,"lon":2.35238},{"lat":48.91111,"lon":2.35243},{"lat":48.911449,"lon":2.352537},{"lat":48.911709,"lon":2.352648},{"lat":48.912022,"lon":2.352818},{"lat":48.912315,"lon":2.353016},{"lat":48.912434,"lon":2.353109},{"lat":48.912659,"lon":2.353301},{"lat":48.912956,"lon":2.353592},{"lat":48.913223,"lon":2.353899},{"lat":48.913494,"lon":2.354257},{"lat":48.913734,"lon":2.354609},{"lat":48.913883,"lon":2.354853},{"lat":48.914425,"lon":2.355829},{"lat":48.916939,"lon":2.360482},{"lat":48.917267,"lon":2.361079},{"lat":48.91811,"lon":2.362559},{"lat":48.91811,"lon":2.362559},{"lat":48.9184,"lon":2.363095},{"lat":48.918579,"lon":2.363446},{"lat":48.918861,"lon":2.364057},{"lat":48.918987,"lon":2.364355},{"lat":48.919147,"lon":2.364774},{"lat":48.919334,"lon":2.365309},{"lat":48.919514,"lon":2.365909},{"lat":48.919765,"lon":2.366878},{"lat":48.922211,"lon":2.37678},{"lat":48.92318,"lon":2.380616},{"lat":48.923428,"lon":2.381631},{"lat":48.92366,"lon":2.382718},{"lat":48.923813,"lon":2.383488},{"lat":48.924061,"lon":2.384958},{"lat":48.924061,"lon":2.384958},{"lat":48.925842,"lon":2.395715},{"lat":48.926186,"lon":2.397924},{"lat":48.926609,"lon":2.400779},{"lat":48.926872,"lon":2.402401},{"lat":48.929916,"lon":2.420778},{"lat":48.930393,"lon":2.423943},{"lat":48.930618,"lon":2.425353},{"lat":48.930618,"lon":2.425353},{"lat":48.930817,"lon":2.426549},{"lat":48.931763,"lon":2.431588},{"lat":48.932247,"lon":2.434381},{"lat":48.932335,"lon":2.434967},{"lat":48.932465,"lon":2.435981},{"lat":48.932579,"lon":2.437064},{"lat":48.932621,"lon":2.437609},{"lat":48.932674,"lon":2.438394},{"lat":48.932716,"lon":2.439245},{"lat":48.932732,"lon":2.439764},{"lat":48.932747,"lon":2.44084},{"lat":48.932674,"lon":2.447437},{"lat":48.932674,"lon":2.44832},{"lat":48.932709,"lon":2.45123},{"lat":48.932709,"lon":2.451989},{"lat":48.932705,"lon":2.45244},{"lat":48.932674,"lon":2.45366},{"lat":48.932674,"lon":2.45366},{"lat":48.932652,"lon":2.454728},{"lat":48.932571,"lon":2.462749},{"lat":48.932552,"lon":2.46394},{"lat":48.932529,"lon":2.464825},{"lat":48.932373,"lon":2.469423},{"lat":48.932343,"lon":2.470615},{"lat":48.93227,"lon":2.476477},{"lat":48.93227,"lon":2.476477},{"lat":48.932095,"lon":2.491748},{"lat":48.932068,"lon":2.492527},{"lat":48.932049,"lon":2.493915},{"lat":48.932056,"lon":2.49493},{"lat":48.932087,"lon":2.496773},{"lat":48.932087,"lon":2.496773},{"lat":48.932098,"lon":2.498153},{"lat":48.932003,"lon":2.50689},{"lat":48.931999,"lon":2.509234},{"lat":48.931973,"lon":2.510414},{"lat":48.931847,"lon":2.515168},{"lat":48.931839,"lon":2.51641},{"lat":48.931858,"lon":2.517184},{"lat":48.931892,"lon":2.517776},{"lat":48.93195,"lon":2.518467},{"lat":48.932076,"lon":2.519506},{"lat":48.932213,"lon":2.520354},{"lat":48.932331,"lon":2.520957},{"lat":48.932549,"lon":2.521899},{"lat":48.932686,"lon":2.522418},{"lat":48.935902,"lon":2.533537},{"lat":48.936039,"lon":2.534034},{"lat":48.936249,"lon":2.53487},{"lat":48.936249,"lon":2.53487},{"lat":48.93961,"lon":2.549152},{"lat":48.940067,"lon":2.551075},{"lat":48.940224,"lon":2.551684},{"lat":48.944454,"lon":2.567665},{"lat":48.944454,"lon":2.567665},{"lat":48.946026,"lon":2.573601},{"lat":48.948841,"lon":2.58477},{"lat":48.953392,"lon":2.604385},{"lat":48.953392,"lon":2.604385},{"lat":48.954369,"lon":2.608619},{"lat":48.954639,"lon":2.609725},{"lat":48.954842,"lon":2.610454},{"lat":48.955116,"lon":2.61128},{"lat":48.955395,"lon":2.611992},{"lat":48.955513,"lon":2.612273},{"lat":48.955715,"lon":2.612708},{"lat":48.956036,"lon":2.613331},{"lat":48.956421,"lon":2.614006},{"lat":48.957035,"lon":2.614943},{"lat":48.957676,"lon":2.61583},{"lat":48.958488,"lon":2.616925},{"lat":48.959286,"lon":2.618075},{"lat":48.961239,"lon":2.620918},{"lat":48.961819,"lon":2.621785},{"lat":48.962894,"lon":2.623452},{"lat":48.96389,"lon":2.624922},{"lat":48.972866,"lon":2.638002},{"lat":48.973068,"lon":2.638279},{"lat":48.973415,"lon":2.638716},{"lat":48.973583,"lon":2.638942},{"lat":48.97419,"lon":2.639826},{"lat":48.974552,"lon":2.640343},{"lat":48.975021,"lon":2.640961},{"lat":48.975925,"lon":2.642283},{"lat":48.975925,"lon":2.642283},{"lat":48.978413,"lon":2.645908},{"lat":48.978722,"lon":2.646441},{"lat":48.979355,"lon":2.647367},{"lat":48.979565,"lon":2.647754},{"lat":48.979691,"lon":2.647963},{"lat":48.986294,"lon":2.657583},{"lat":48.991901,"lon":2.665778},{"lat":48.991901,"lon":2.665778},{"lat":48.993423,"lon":2.668005},{"lat":48.993824,"lon":2.668562},{"lat":48.994183,"lon":2.669021},{"lat":48.994579,"lon":2.669471},{"lat":48.994759,"lon":2.669662},{"lat":48.995193,"lon":2.670071},{"lat":48.995609,"lon":2.670422},{"lat":49.006233,"lon":2.678745},{"lat":49.008423,"lon":2.680467},{"lat":49.008423,"lon":2.680467},{"lat":49.030327,"lon":2.697661},{"lat":49.031158,"lon":2.698323},{"lat":49.031326,"lon":2.698446},{"lat":49.032127,"lon":2.69907},{"lat":49.032127,"lon":2.69907},{"lat":49.036404,"lon":2.702438},{"lat":49.044853,"lon":2.709076},{"lat":49.04567,"lon":2.709698},{"lat":49.046253,"lon":2.710123},{"lat":49.04681,"lon":2.710512},{"lat":49.068531,"lon":2.724939},{"lat":49.085869,"lon":2.736485},{"lat":49.091187,"lon":2.740017},{"lat":49.09174,"lon":2.740395},{"lat":49.092094,"lon":2.740659},{"lat":49.092426,"lon":2.740937},{"lat":49.092724,"lon":2.741213},{"lat":49.092937,"lon":2.741425},{"lat":49.096336,"lon":2.745026},{"lat":49.096336,"lon":2.745026},{"lat":49.113773,"lon":2.763513},{"lat":49.142818,"lon":2.794348},{"lat":49.142818,"lon":2.794348},{"lat":49.14957,"lon":2.801528},{"lat":49.150032,"lon":2.802011},{"lat":49.150406,"lon":2.802376},{"lat":49.150707,"lon":2.802646},{"lat":49.150959,"lon":2.802852},{"lat":49.151207,"lon":2.803041},{"lat":49.15152,"lon":2.803258},{"lat":49.151756,"lon":2.80341},{"lat":49.15218,"lon":2.803664},{"lat":49.166088,"lon":2.811834},{"lat":49.187275,"lon":2.824302},{"lat":49.187733,"lon":2.824583},{"lat":49.188282,"lon":2.824938},{"lat":49.188763,"lon":2.82526},{"lat":49.189308,"lon":2.825644},{"lat":49.190029,"lon":2.826178},{"lat":49.190353,"lon":2.826427},{"lat":49.190948,"lon":2.826904},{"lat":49.191578,"lon":2.827432},{"lat":49.192448,"lon":2.828202},{"lat":49.19286,"lon":2.828586},{"lat":49.193764,"lon":2.829467},{"lat":49.194305,"lon":2.830021},{"lat":49.194736,"lon":2.83048},{"lat":49.195507,"lon":2.831335},{"lat":49.19582,"lon":2.831694},{"lat":49.19651,"lon":2.832515},{"lat":49.196873,"lon":2.832964},{"lat":49.197521,"lon":2.833801},{"lat":49.200977,"lon":2.838472},{"lat":49.200977,"lon":2.838472},{"lat":49.227097,"lon":2.873762},{"lat":49.22794,"lon":2.874913},{"lat":49.228188,"lon":2.875285},{"lat":49.228382,"lon":2.875592},{"lat":49.228718,"lon":2.876163},{"lat":49.228912,"lon":2.876526},{"lat":49.229069,"lon":2.876837},{"lat":49.22934,"lon":2.877416},{"lat":49.22953,"lon":2.877857},{"lat":49.22966,"lon":2.878174},{"lat":49.2299,"lon":2.878815},{"lat":49.230019,"lon":2.879148},{"lat":49.23024,"lon":2.879859},{"lat":49.230434,"lon":2.880566},{"lat":49.230576,"lon":2.881162},{"lat":49.230717,"lon":2.881877},{"lat":49.230804,"lon":2.88239},{"lat":49.230904,"lon":2.88316},{"lat":49.230953,"lon":2.883637},{"lat":49.230995,"lon":2.884203},{"lat":49.231106,"lon":2.88649}],"IDFM:shp_2_68":[{"lat":49.231071,"lon":2.886496},{"lat":49.230995,"lon":2.884792},{"lat":49.230942,"lon":2.88389},{"lat":49.230904,"lon":2.883488},{"lat":49.230827,"lon":2.8828},{"lat":49.23077,"lon":2.882399},{"lat":49.230633,"lon":2.881603},{"lat":49.230541,"lon":2.881177},{"lat":49.230404,"lon":2.880582},{"lat":49.230209,"lon":2.879878},{"lat":49.230072,"lon":2.879424},{"lat":49.22987,"lon":2.878837},{"lat":49.229752,"lon":2.878516},{"lat":49.229504,"lon":2.877884},{"lat":49.229313,"lon":2.877443},{"lat":49.229038,"lon":2.876864},{"lat":49.228691,"lon":2.876196},{"lat":49.228359,"lon":2.875628},{"lat":49.228165,"lon":2.875322},{"lat":49.227913,"lon":2.874948},{"lat":49.227074,"lon":2.8738},{"lat":49.200962,"lon":2.838515},{"lat":49.200962,"lon":2.838515},{"lat":49.197502,"lon":2.833843},{"lat":49.196854,"lon":2.833005},{"lat":49.196487,"lon":2.832556},{"lat":49.195801,"lon":2.831736},{"lat":49.195488,"lon":2.831376},{"lat":49.194725,"lon":2.830527},{"lat":49.19429,"lon":2.830068},{"lat":49.193748,"lon":2.829509},{"lat":49.192844,"lon":2.828632},{"lat":49.192432,"lon":2.828248},{"lat":49.191563,"lon":2.827477},{"lat":49.190933,"lon":2.826949},{"lat":49.190338,"lon":2.826473},{"lat":49.189579,"lon":2.825896},{"lat":49.188751,"lon":2.825309},{"lat":49.188274,"lon":2.824986},{"lat":49.187721,"lon":2.82463},{"lat":49.187263,"lon":2.82435},{"lat":49.166077,"lon":2.811882},{"lat":49.152168,"lon":2.803712},{"lat":49.151745,"lon":2.803458},{"lat":49.151344,"lon":2.803194},{"lat":49.150948,"lon":2.802898},{"lat":49.150696,"lon":2.802693},{"lat":49.150391,"lon":2.802422},{"lat":49.150013,"lon":2.802054},{"lat":49.149551,"lon":2.80157},{"lat":49.142803,"lon":2.794393},{"lat":49.142803,"lon":2.794393},{"lat":49.113617,"lon":2.763412},{"lat":49.096306,"lon":2.745055},{"lat":49.096306,"lon":2.745055},{"lat":49.092915,"lon":2.741466},{"lat":49.092709,"lon":2.741259},{"lat":49.092407,"lon":2.74098},{"lat":49.092079,"lon":2.740705},{"lat":49.091728,"lon":2.740442},{"lat":49.091175,"lon":2.740064},{"lat":49.06852,"lon":2.724986},{"lat":49.046799,"lon":2.710559},{"lat":49.046238,"lon":2.710169},{"lat":49.045654,"lon":2.709743},{"lat":49.044838,"lon":2.709122},{"lat":49.039623,"lon":2.705031},{"lat":49.032112,"lon":2.699116},{"lat":49.032112,"lon":2.699116},{"lat":49.031124,"lon":2.698352},{"lat":49.030949,"lon":2.698208},{"lat":49.027187,"lon":2.695246},{"lat":49.007301,"lon":2.679644},{"lat":49.007301,"lon":2.679644},{"lat":48.995594,"lon":2.670466},{"lat":48.995174,"lon":2.670115},{"lat":48.995033,"lon":2.669986},{"lat":48.994743,"lon":2.669705},{"lat":48.99456,"lon":2.669512},{"lat":48.994343,"lon":2.669273},{"lat":48.99416,"lon":2.669058},{"lat":48.993797,"lon":2.668597},{"lat":48.993645,"lon":2.668386},{"lat":48.993198,"lon":2.667747},{"lat":48.991467,"lon":2.665202},{"lat":48.990746,"lon":2.664158},{"lat":48.990746,"lon":2.664158},{"lat":48.988667,"lon":2.661113},{"lat":48.98167,"lon":2.650916},{"lat":48.981075,"lon":2.649978},{"lat":48.979691,"lon":2.647963},{"lat":48.979565,"lon":2.647754},{"lat":48.979355,"lon":2.647367},{"lat":48.978722,"lon":2.646441},{"lat":48.978413,"lon":2.645908},{"lat":48.975925,"lon":2.642283},{"lat":48.975925,"lon":2.642283},{"lat":48.975021,"lon":2.640961},{"lat":48.974552,"lon":2.640343},{"lat":48.97419,"lon":2.639826},{"lat":48.973583,"lon":2.638942},{"lat":48.973415,"lon":2.638716},{"lat":48.973068,"lon":2.638279},{"lat":48.972893,"lon":2.638041},{"lat":48.972359,"lon":2.637261},{"lat":48.971825,"lon":2.636551},{"lat":48.963081,"lon":2.623812},{"lat":48.96246,"lon":2.62294},{"lat":48.961494,"lon":2.621643},{"lat":48.960789,"lon":2.620654},{"lat":48.958672,"lon":2.617563},{"lat":48.957752,"lon":2.616176},{"lat":48.957058,"lon":2.615093},{"lat":48.956402,"lon":2.614041},{"lat":48.956131,"lon":2.613577},{"lat":48.955856,"lon":2.613068},{"lat":48.955738,"lon":2.612835},{"lat":48.955593,"lon":2.612532},{"lat":48.955368,"lon":2.61202},{"lat":48.955181,"lon":2.611557},{"lat":48.954956,"lon":2.610929},{"lat":48.954769,"lon":2.610331},{"lat":48.954525,"lon":2.609411},{"lat":48.954338,"lon":2.608631},{"lat":48.952816,"lon":2.602059},{"lat":48.952816,"lon":2.602059},{"lat":48.949142,"lon":2.586205},{"lat":48.948765,"lon":2.584613},{"lat":48.945995,"lon":2.573628},{"lat":48.943756,"lon":2.565176},{"lat":48.943756,"lon":2.565176},{"lat":48.940033,"lon":2.551093},{"lat":48.936218,"lon":2.534888},{"lat":48.936218,"lon":2.534888},{"lat":48.936008,"lon":2.534054},{"lat":48.935871,"lon":2.533558},{"lat":48.932739,"lon":2.522724},{"lat":48.932522,"lon":2.521922},{"lat":48.932301,"lon":2.520964},{"lat":48.932175,"lon":2.520327},{"lat":48.932076,"lon":2.519723},{"lat":48.931965,"lon":2.518915},{"lat":48.931896,"lon":2.518246},{"lat":48.931839,"lon":2.517445},{"lat":48.931805,"lon":2.516403},{"lat":48.931808,"lon":2.515767},{"lat":48.931816,"lon":2.515116},{"lat":48.931961,"lon":2.509732},{"lat":48.931969,"lon":2.509265},{"lat":48.931973,"lon":2.506394},{"lat":48.932068,"lon":2.498261},{"lat":48.932068,"lon":2.497622},{"lat":48.932037,"lon":2.495599},{"lat":48.932037,"lon":2.495599},{"lat":48.932014,"lon":2.494095},{"lat":48.932022,"lon":2.493208},{"lat":48.932079,"lon":2.49062},{"lat":48.93219,"lon":2.480733},{"lat":48.932171,"lon":2.477563},{"lat":48.932186,"lon":2.476502},{"lat":48.932186,"lon":2.476502},{"lat":48.932251,"lon":2.473355},{"lat":48.932297,"lon":2.46891},{"lat":48.93232,"lon":2.467754},{"lat":48.932449,"lon":2.46167},{"lat":48.93259,"lon":2.456867},{"lat":48.932621,"lon":2.454705},{"lat":48.932644,"lon":2.453497},{"lat":48.932644,"lon":2.453497},{"lat":48.932671,"lon":2.452448},{"lat":48.932678,"lon":2.451695},{"lat":48.93264,"lon":2.447757},{"lat":48.932716,"lon":2.440837},{"lat":48.932705,"lon":2.439753},{"lat":48.932663,"lon":2.438682},{"lat":48.932594,"lon":2.437628},{"lat":48.932487,"lon":2.436482},{"lat":48.932434,"lon":2.435985},{"lat":48.932301,"lon":2.434956},{"lat":48.932213,"lon":2.434367},{"lat":48.931934,"lon":2.432744},{"lat":48.931736,"lon":2.431611},{"lat":48.930855,"lon":2.426949},{"lat":48.930588,"lon":2.425374},{"lat":48.930588,"lon":2.425374},{"lat":48.930439,"lon":2.424471},{"lat":48.929775,"lon":2.420126},{"lat":48.926731,"lon":2.401742},{"lat":48.926579,"lon":2.400801},{"lat":48.926174,"lon":2.398086},{"lat":48.925812,"lon":2.395725},{"lat":48.92403,"lon":2.384966},{"lat":48.92403,"lon":2.384966},{"lat":48.923779,"lon":2.383502},{"lat":48.923626,"lon":2.382727},{"lat":48.923393,"lon":2.381644},{"lat":48.923153,"lon":2.380646},{"lat":48.922348,"lon":2.377458},{"lat":48.921268,"lon":2.37313},{"lat":48.920063,"lon":2.36823},{"lat":48.919842,"lon":2.367398},{"lat":48.91959,"lon":2.366565},{"lat":48.919327,"lon":2.365783},{"lat":48.919125,"lon":2.365254},{"lat":48.918903,"lon":2.364711},{"lat":48.918655,"lon":2.364178},{"lat":48.917969,"lon":2.362823},{"lat":48.917969,"lon":2.362823},{"lat":48.917358,"lon":2.361675},{"lat":48.917,"lon":2.360919},{"lat":48.916683,"lon":2.360283},{"lat":48.914474,"lon":2.356166},{"lat":48.914093,"lon":2.355502},{"lat":48.913601,"lon":2.354657},{"lat":48.913368,"lon":2.354302},{"lat":48.913113,"lon":2.35397},{"lat":48.912952,"lon":2.353783},{"lat":48.912785,"lon":2.353605},{"lat":48.912518,"lon":2.353357},{"lat":48.912342,"lon":2.353212},{"lat":48.912163,"lon":2.353079},{"lat":48.911991,"lon":2.352967},{"lat":48.911671,"lon":2.352786},{"lat":48.91151,"lon":2.352713},{"lat":48.911129,"lon":2.352576},{"lat":48.910862,"lon":2.352518},{"lat":48.910637,"lon":2.352486},{"lat":48.91045,"lon":2.35247},{"lat":48.910305,"lon":2.352466},{"lat":48.910099,"lon":2.35247},{"lat":48.909832,"lon":2.352491},{"lat":48.909489,"lon":2.352544},{"lat":48.909092,"lon":2.352641},{"lat":48.908833,"lon":2.352724},{"lat":48.908634,"lon":2.352796},{"lat":48.90802,"lon":2.35304},{"lat":48.906921,"lon":2.353433},{"lat":48.906357,"lon":2.353646},{"lat":48.905624,"lon":2.353951},{"lat":48.903656,"lon":2.354797},{"lat":48.903435,"lon":2.354877},{"lat":48.903149,"lon":2.354949},{"lat":48.902866,"lon":2.354992},{"lat":48.902714,"lon":2.355001},{"lat":48.902512,"lon":2.354999},{"lat":48.902321,"lon":2.354986},{"lat":48.902077,"lon":2.35495},{"lat":48.901585,"lon":2.354856},{"lat":48.901283,"lon":2.354825},{"lat":48.900883,"lon":2.354831},{"lat":48.899235,"lon":2.355023},{"lat":48.89793,"lon":2.355194},{"lat":48.897667,"lon":2.355242},{"lat":48.897224,"lon":2.355344},{"lat":48.896927,"lon":2.355397},{"lat":48.896294,"lon":2.355452},{"lat":48.896049,"lon":2.355499},{"lat":48.895443,"lon":2.355643},{"lat":48.894886,"lon":2.355795},{"lat":48.893875,"lon":2.356128},{"lat":48.89307,"lon":2.356401},{"lat":48.892666,"lon":2.356551},{"lat":48.892414,"lon":2.356657},{"lat":48.892036,"lon":2.356838},{"lat":48.891628,"lon":2.357011},{"lat":48.891113,"lon":2.357244},{"lat":48.890835,"lon":2.357357},{"lat":48.890553,"lon":2.357457},{"lat":48.890217,"lon":2.35755},{"lat":48.889816,"lon":2.357628},{"lat":48.888393,"lon":2.35786},{"lat":48.887486,"lon":2.357943},{"lat":48.886402,"lon":2.35802},{"lat":48.885845,"lon":2.35798},{"lat":48.884312,"lon":2.357993},{"lat":48.883568,"lon":2.358015},{"lat":48.883125,"lon":2.357999},{"lat":48.882969,"lon":2.357986},{"lat":48.882751,"lon":2.357955},{"lat":48.882294,"lon":2.357846},{"lat":48.882133,"lon":2.357795},{"lat":48.881969,"lon":2.357732},{"lat":48.881393,"lon":2.357473}],"IDFM:shp_2_264":[{"lat":48.975925,"lon":2.642283},{"lat":48.978413,"lon":2.645908},{"lat":48.978722,"lon":2.646441},{"lat":48.979355,"lon":2.647367},{"lat":48.979565,"lon":2.647754},{"lat":48.979691,"lon":2.647963},{"lat":48.986294,"lon":2.657583},{"lat":48.991901,"lon":2.665778},{"lat":48.991901,"lon":2.665778},{"lat":48.993423,"lon":2.668005},{"lat":48.993824,"lon":2.668562},{"lat":48.994183,"lon":2.669021},{"lat":48.994579,"lon":2.669471},{"lat":48.994759,"lon":2.669662},{"lat":48.995193,"lon":2.670071},{"lat":48.995609,"lon":2.670422},{"lat":49.006233,"lon":2.678745},{"lat":49.008423,"lon":2.680467},{"lat":49.008423,"lon":2.680467},{"lat":49.030327,"lon":2.697661},{"lat":49.031158,"lon":2.698323},{"lat":49.031326,"lon":2.698446},{"lat":49.032127,"lon":2.69907},{"lat":49.032127,"lon":2.69907},{"lat":49.036404,"lon":2.702438},{"lat":49.044853,"lon":2.709076},{"lat":49.04567,"lon":2.709698},{"lat":49.046253,"lon":2.710123},{"lat":49.04681,"lon":2.710512},{"lat":49.068531,"lon":2.724939},{"lat":49.085869,"lon":2.736485},{"lat":49.091187,"lon":2.740017},{"lat":49.09174,"lon":2.740395},{"lat":49.092094,"lon":2.740659},{"lat":49.092426,"lon":2.740937},{"lat":49.092724,"lon":2.741213},{"lat":49.092937,"lon":2.741425},{"lat":49.096336,"lon":2.745026},{"lat":49.096336,"lon":2.745026},{"lat":49.113773,"lon":2.763513},{"lat":49.142818,"lon":2.794348},{"lat":49.142818,"lon":2.794348},{"lat":49.14957,"lon":2.801528},{"lat":49.150032,"lon":2.802011},{"lat":49.150406,"lon":2.802376},{"lat":49.150707,"lon":2.802646},{"lat":49.150959,"lon":2.802852},{"lat":49.151207,"lon":2.803041},{"lat":49.15152,"lon":2.803258},{"lat":49.151756,"lon":2.80341},{"lat":49.15218,"lon":2.803664},{"lat":49.166088,"lon":2.811834},{"lat":49.187275,"lon":2.824302},{"lat":49.187733,"lon":2.824583},{"lat":49.188282,"lon":2.824938},{"lat":49.188763,"lon":2.82526},{"lat":49.189308,"lon":2.825644},{"lat":49.190029,"lon":2.826178},{"lat":49.190353,"lon":2.826427},{"lat":49.190948,"lon":2.826904},{"lat":49.191578,"lon":2.827432},{"lat":49.192448,"lon":2.828202},{"lat":49.19286,"lon":2.828586},{"lat":49.193764,"lon":2.829467},{"lat":49.194305,"lon":2.830021},{"lat":49.194736,"lon":2.83048},{"lat":49.195507,"lon":2.831335},{"lat":49.19582,"lon":2.831694},{"lat":49.19651,"lon":2.832515},{"lat":49.196873,"lon":2.832964},{"lat":49.197521,"lon":2.833801},{"lat":49.200977,"lon":2.838472},{"lat":49.200977,"lon":2.838472},{"lat":49.227097,"lon":2.873762},{"lat":49.22794,"lon":2.874913},{"lat":49.228188,"lon":2.875285},{"lat":49.228382,"lon":2.875592},{"lat":49.228718,"lon":2.876163},{"lat":49.228912,"lon":2.876526},{"lat":49.229069,"lon":2.876837},{"lat":49.22934,"lon":2.877416},{"lat":49.22953,"lon":2.877857},{"lat":49.22966,"lon":2.878174},{"lat":49.2299,"lon":2.878815},{"lat":49.230019,"lon":2.879148},{"lat":49.23024,"lon":2.879859},{"lat":49.230434,"lon":2.880566},{"lat":49.230576,"lon":2.881162},{"lat":49.230717,"lon":2.881877},{"lat":49.230804,"lon":2.88239},{"lat":49.230904,"lon":2.88316},{"lat":49.230953,"lon":2.883637},{"lat":49.230995,"lon":2.884203},{"lat":49.231106,"lon":2.88649}],"IDFM:shp_2_67":[{"lat":49.231071,"lon":2.886496},{"lat":49.230995,"lon":2.884792},{"lat":49.230942,"lon":2.88389},{"lat":49.230904,"lon":2.883488},{"lat":49.230827,"lon":2.8828},{"lat":49.23077,"lon":2.882399},{"lat":49.230633,"lon":2.881603},{"lat":49.230541,"lon":2.881177},{"lat":49.230404,"lon":2.880582},{"lat":49.230209,"lon":2.879878},{"lat":49.230072,"lon":2.879424},{"lat":49.22987,"lon":2.878837},{"lat":49.229752,"lon":2.878516},{"lat":49.229504,"lon":2.877884},{"lat":49.229313,"lon":2.877443},{"lat":49.229038,"lon":2.876864},{"lat":49.228691,"lon":2.876196},{"lat":49.228359,"lon":2.875628},{"lat":49.228165,"lon":2.875322},{"lat":49.227913,"lon":2.874948},{"lat":49.227074,"lon":2.8738},{"lat":49.200962,"lon":2.838515},{"lat":49.200962,"lon":2.838515},{"lat":49.197502,"lon":2.833843},{"lat":49.196854,"lon":2.833005},{"lat":49.196487,"lon":2.832556},{"lat":49.195801,"lon":2.831736},{"lat":49.195488,"lon":2.831376},{"lat":49.194725,"lon":2.830527},{"lat":49.19429,"lon":2.830068},{"lat":49.193748,"lon":2.829509},{"lat":49.192844,"lon":2.828632},{"lat":49.192432,"lon":2.828248},{"lat":49.191563,"lon":2.827477},{"lat":49.190933,"lon":2.826949},{"lat":49.190338,"lon":2.826473},{"lat":49.189579,"lon":2.825896},{"lat":49.188751,"lon":2.825309},{"lat":49.188274,"lon":2.824986},{"lat":49.187721,"lon":2.82463},{"lat":49.187263,"lon":2.82435},{"lat":49.166077,"lon":2.811882},{"lat":49.152168,"lon":2.803712},{"lat":49.151745,"lon":2.803458},{"lat":49.151344,"lon":2.803194},{"lat":49.150948,"lon":2.802898},{"lat":49.150696,"lon":2.802693},{"lat":49.150391,"lon":2.802422},{"lat":49.150013,"lon":2.802054},{"lat":49.149551,"lon":2.80157},{"lat":49.142803,"lon":2.794393},{"lat":49.142803,"lon":2.794393},{"lat":49.113617,"lon":2.763412},{"lat":49.096306,"lon":2.745055},{"lat":49.096306,"lon":2.745055},{"lat":49.092915,"lon":2.741466},{"lat":49.092709,"lon":2.741259},{"lat":49.092407,"lon":2.74098},{"lat":49.092079,"lon":2.740705},{"lat":49.091728,"lon":2.740442},{"lat":49.091175,"lon":2.740064},{"lat":49.06852,"lon":2.724986},{"lat":49.046799,"lon":2.710559},{"lat":49.046238,"lon":2.710169},{"lat":49.045654,"lon":2.709743},{"lat":49.044838,"lon":2.709122},{"lat":49.039623,"lon":2.705031},{"lat":49.032112,"lon":2.699116},{"lat":49.032112,"lon":2.699116},{"lat":49.031124,"lon":2.698352},{"lat":49.030949,"lon":2.698208},{"lat":49.027187,"lon":2.695246},{"lat":49.007301,"lon":2.679644},{"lat":49.007301,"lon":2.679644},{"lat":48.995594,"lon":2.670466},{"lat":48.995174,"lon":2.670115},{"lat":48.995033,"lon":2.669986},{"lat":48.994743,"lon":2.669705},{"lat":48.99456,"lon":2.669512},{"lat":48.994343,"lon":2.669273},{"lat":48.99416,"lon":2.669058},{"lat":48.993797,"lon":2.668597},{"lat":48.993645,"lon":2.668386},{"lat":48.993198,"lon":2.667747},{"lat":48.991467,"lon":2.665202},{"lat":48.990746,"lon":2.664158},{"lat":48.990746,"lon":2.664158},{"lat":48.988667,"lon":2.661113},{"lat":48.98167,"lon":2.650916},{"lat":48.981075,"lon":2.649978},{"lat":48.979691,"lon":2.647963},{"lat":48.979565,"lon":2.647754},{"lat":48.979355,"lon":2.647367},{"lat":48.978722,"lon":2.646441},{"lat":48.978413,"lon":2.645908},{"lat":48.975925,"lon":2.642283}],"IDFM:shp_2_206":[{"lat":48.881462,"lon":2.357134},{"lat":48.882149,"lon":2.35744},{"lat":48.882404,"lon":2.357531},{"lat":48.882759,"lon":2.35763},{"lat":48.883118,"lon":2.357696},{"lat":48.883362,"lon":2.357724},{"lat":48.884266,"lon":2.357777},{"lat":48.884686,"lon":2.357885},{"lat":48.886402,"lon":2.357887},{"lat":48.888329,"lon":2.357741},{"lat":48.889812,"lon":2.357518},{"lat":48.890118,"lon":2.357456},{"lat":48.890301,"lon":2.35741},{"lat":48.890507,"lon":2.357346},{"lat":48.890842,"lon":2.357215},{"lat":48.891056,"lon":2.357121},{"lat":48.89151,"lon":2.356897},{"lat":48.892315,"lon":2.356521},{"lat":48.894268,"lon":2.355581},{"lat":48.894798,"lon":2.355371},{"lat":48.896488,"lon":2.354803},{"lat":48.896805,"lon":2.354713},{"lat":48.89719,"lon":2.354617},{"lat":48.897442,"lon":2.354567},{"lat":48.897861,"lon":2.354514},{"lat":48.898102,"lon":2.354499},{"lat":48.898979,"lon":2.354472},{"lat":48.899353,"lon":2.354452},{"lat":48.899689,"lon":2.354422},{"lat":48.900089,"lon":2.354361},{"lat":48.900913,"lon":2.354175},{"lat":48.901546,"lon":2.354024},{"lat":48.901779,"lon":2.353945},{"lat":48.902561,"lon":2.353642},{"lat":48.903008,"lon":2.353502},{"lat":48.903519,"lon":2.353381},{"lat":48.904167,"lon":2.353274},{"lat":48.905918,"lon":2.353014},{"lat":48.907265,"lon":2.352858},{"lat":48.907887,"lon":2.352739},{"lat":48.908497,"lon":2.352578},{"lat":48.909431,"lon":2.352269},{"lat":48.909622,"lon":2.352216},{"lat":48.910198,"lon":2.352095},{"lat":48.910522,"lon":2.352046},{"lat":48.910732,"lon":2.352026},{"lat":48.911354,"lon":2.352001},{"lat":48.911758,"lon":2.351971},{"lat":48.911903,"lon":2.351955},{"lat":48.912167,"lon":2.351905},{"lat":48.912632,"lon":2.351779},{"lat":48.912819,"lon":2.351714},{"lat":48.914829,"lon":2.350974},{"lat":48.91534,"lon":2.350807},{"lat":48.915749,"lon":2.350694},{"lat":48.919914,"lon":2.349695},{"lat":48.920109,"lon":2.349634},{"lat":48.920391,"lon":2.349528},{"lat":48.921398,"lon":2.349089},{"lat":48.921768,"lon":2.348963},{"lat":48.922497,"lon":2.348764},{"lat":48.922947,"lon":2.348654},{"lat":48.923546,"lon":2.348523},{"lat":48.924194,"lon":2.348366},{"lat":48.925236,"lon":2.348084},{"lat":48.927361,"lon":2.347456},{"lat":48.930992,"lon":2.346543},{"lat":48.931499,"lon":2.346426},{"lat":48.932175,"lon":2.346258},{"lat":48.934162,"lon":2.345742},{"lat":48.935188,"lon":2.345495},{"lat":48.935188,"lon":2.345495},{"lat":48.935425,"lon":2.34544},{"lat":48.936203,"lon":2.345287},{"lat":48.936878,"lon":2.345143},{"lat":48.938469,"lon":2.344743},{"lat":48.939579,"lon":2.344455},{"lat":48.9398,"lon":2.344408},{"lat":48.940121,"lon":2.344357},{"lat":48.940632,"lon":2.344302},{"lat":48.941135,"lon":2.344296},{"lat":48.941345,"lon":2.344304},{"lat":48.941769,"lon":2.344349},{"lat":48.942108,"lon":2.344404},{"lat":48.942593,"lon":2.344519},{"lat":48.943001,"lon":2.34465},{"lat":48.943256,"lon":2.344748},{"lat":48.943695,"lon":2.344949},{"lat":48.944096,"lon":2.345172},{"lat":48.944305,"lon":2.345301},{"lat":48.94453,"lon":2.345448},{"lat":48.944981,"lon":2.345779},{"lat":48.9454,"lon":2.346134},{"lat":48.945621,"lon":2.346335},{"lat":48.945995,"lon":2.346707},{"lat":48.946316,"lon":2.347064},{"lat":48.946522,"lon":2.347308},{"lat":48.946739,"lon":2.347586},{"lat":48.946987,"lon":2.347922},{"lat":48.948948,"lon":2.350703},{"lat":48.95113,"lon":2.353819},{"lat":48.952057,"lon":2.355133},{"lat":48.952656,"lon":2.355961},{"lat":48.953125,"lon":2.356597},{"lat":48.953686,"lon":2.357388},{"lat":48.954353,"lon":2.358342},{"lat":48.955799,"lon":2.360454},{"lat":48.959751,"lon":2.366094},{"lat":48.960468,"lon":2.367105},{"lat":48.960724,"lon":2.367448},{"lat":48.96117,"lon":2.368027},{"lat":48.961666,"lon":2.368722},{"lat":48.96241,"lon":2.369827},{"lat":48.962708,"lon":2.370292},{"lat":48.963299,"lon":2.371273},{"lat":48.963577,"lon":2.371696},{"lat":48.96447,"lon":2.372971},{"lat":48.96677,"lon":2.376156},{"lat":48.971684,"lon":2.383152},{"lat":48.972679,"lon":2.384586},{"lat":48.973732,"lon":2.386162},{"lat":48.975121,"lon":2.388153},{"lat":48.975742,"lon":2.38901},{"lat":48.9767,"lon":2.390274},{"lat":48.977234,"lon":2.391025},{"lat":48.977482,"lon":2.391393},{"lat":48.978546,"lon":2.393027},{"lat":48.985233,"lon":2.40257},{"lat":48.986282,"lon":2.404081},{"lat":48.986927,"lon":2.405084},{"lat":48.991344,"lon":2.412037},{"lat":48.993702,"lon":2.415735},{"lat":48.994049,"lon":2.41629},{"lat":48.994049,"lon":2.41629},{"lat":49.006344,"lon":2.435626},{"lat":49.010139,"lon":2.441612},{"lat":49.011326,"lon":2.44347},{"lat":49.011974,"lon":2.444508},{"lat":49.018822,"lon":2.455284},{"lat":49.020828,"lon":2.458448},{"lat":49.021233,"lon":2.459158},{"lat":49.023327,"lon":2.462455},{"lat":49.023327,"lon":2.462455},{"lat":49.024525,"lon":2.464342},{"lat":49.024834,"lon":2.464753},{"lat":49.024906,"lon":2.464866},{"lat":49.025974,"lon":2.466551},{"lat":49.026779,"lon":2.467776},{"lat":49.02713,"lon":2.46832},{"lat":49.028179,"lon":2.470027},{"lat":49.031357,"lon":2.475041},{"lat":49.031647,"lon":2.475491},{"lat":49.03196,"lon":2.47596},{"lat":49.032539,"lon":2.476801},{"lat":49.033348,"lon":2.478055},{"lat":49.033649,"lon":2.478538},{"lat":49.034771,"lon":2.480417},{"lat":49.035095,"lon":2.480937},{"lat":49.041229,"lon":2.490609},{"lat":49.041748,"lon":2.491398},{"lat":49.042049,"lon":2.491829},{"lat":49.042839,"lon":2.492911},{"lat":49.061405,"lon":2.518144},{"lat":49.062187,"lon":2.519191},{"lat":49.062607,"lon":2.519699},{"lat":49.062931,"lon":2.520057},{"lat":49.063335,"lon":2.520454},{"lat":49.063671,"lon":2.520747},{"lat":49.063896,"lon":2.52093},{"lat":49.064198,"lon":2.521154},{"lat":49.064575,"lon":2.521405},{"lat":49.064846,"lon":2.521567},{"lat":49.065281,"lon":2.521792},{"lat":49.065662,"lon":2.521962},{"lat":49.066071,"lon":2.522111},{"lat":49.066265,"lon":2.522171},{"lat":49.066696,"lon":2.522277},{"lat":49.067188,"lon":2.522361},{"lat":49.067513,"lon":2.5224},{"lat":49.071072,"lon":2.522744},{"lat":49.091576,"lon":2.524683},{"lat":49.094296,"lon":2.525005},{"lat":49.099579,"lon":2.525506},{"lat":49.099579,"lon":2.525506},{"lat":49.109245,"lon":2.526422},{"lat":49.109505,"lon":2.526435},{"lat":49.109947,"lon":2.526438},{"lat":49.11034,"lon":2.526412},{"lat":49.110516,"lon":2.526391},{"lat":49.110886,"lon":2.526329},{"lat":49.11113,"lon":2.526274},{"lat":49.111446,"lon":2.526187},{"lat":49.111839,"lon":2.526054},{"lat":49.112053,"lon":2.52597},{"lat":49.112389,"lon":2.52582},{"lat":49.112736,"lon":2.525642},{"lat":49.112961,"lon":2.525514},{"lat":49.113174,"lon":2.525382},{"lat":49.11351,"lon":2.525154},{"lat":49.113667,"lon":2.525038},{"lat":49.114002,"lon":2.524771},{"lat":49.114468,"lon":2.524367},{"lat":49.114799,"lon":2.524051},{"lat":49.115227,"lon":2.523614},{"lat":49.115543,"lon":2.523257},{"lat":49.115849,"lon":2.522895},{"lat":49.116261,"lon":2.522367},{"lat":49.116539,"lon":2.521979},{"lat":49.116898,"lon":2.521447},{"lat":49.117325,"lon":2.520774},{"lat":49.119709,"lon":2.516845},{"lat":49.120663,"lon":2.515316},{"lat":49.121513,"lon":2.514002},{"lat":49.129597,"lon":2.501772},{"lat":49.130035,"lon":2.501065},{"lat":49.130657,"lon":2.500039},{"lat":49.131058,"lon":2.499398},{"lat":49.134056,"lon":2.494858},{"lat":49.134583,"lon":2.494094},{"lat":49.134872,"lon":2.493692},{"lat":49.135231,"lon":2.493227},{"lat":49.135632,"lon":2.492724},{"lat":49.135857,"lon":2.492451},{"lat":49.136337,"lon":2.491902},{"lat":49.136723,"lon":2.491493},{"lat":49.137222,"lon":2.490987},{"lat":49.137817,"lon":2.490421},{"lat":49.138306,"lon":2.489974},{"lat":49.138306,"lon":2.489974},{"lat":49.138817,"lon":2.489522},{"lat":49.139263,"lon":2.489143},{"lat":49.141705,"lon":2.487109},{"lat":49.142654,"lon":2.4863},{"lat":49.143639,"lon":2.485446},{"lat":49.145828,"lon":2.483512},{"lat":49.146423,"lon":2.482984},{"lat":49.146736,"lon":2.482693},{"lat":49.147278,"lon":2.48217},{"lat":49.147678,"lon":2.481753},{"lat":49.155876,"lon":2.472873},{"lat":49.156456,"lon":2.472277},{"lat":49.156918,"lon":2.471841},{"lat":49.157364,"lon":2.471458},{"lat":49.157616,"lon":2.471254},{"lat":49.15802,"lon":2.470958},{"lat":49.158401,"lon":2.470698},{"lat":49.15881,"lon":2.47045},{"lat":49.159233,"lon":2.470214},{"lat":49.159622,"lon":2.470021},{"lat":49.160133,"lon":2.469788},{"lat":49.160805,"lon":2.469505},{"lat":49.174446,"lon":2.463933},{"lat":49.182629,"lon":2.460574},{"lat":49.183582,"lon":2.460203},{"lat":49.183891,"lon":2.460091},{"lat":49.184223,"lon":2.45998},{"lat":49.184574,"lon":2.459876},{"lat":49.184875,"lon":2.459796},{"lat":49.185329,"lon":2.459688},{"lat":49.185863,"lon":2.45958},{"lat":49.18647,"lon":2.459478},{"lat":49.187073,"lon":2.459393},{"lat":49.187073,"lon":2.459393},{"lat":49.18922,"lon":2.459121},{"lat":49.18964,"lon":2.459063},{"lat":49.191765,"lon":2.45883},{"lat":49.192955,"lon":2.458673},{"lat":49.198338,"lon":2.457905},{"lat":49.198978,"lon":2.457824},{"lat":49.199783,"lon":2.457727},{"lat":49.200191,"lon":2.457686},{"lat":49.200714,"lon":2.457619},{"lat":49.202168,"lon":2.457412},{"lat":49.204544,"lon":2.457088},{"lat":49.205952,"lon":2.456874},{"lat":49.20639,"lon":2.456798},{"lat":49.206635,"lon":2.456747},{"lat":49.207386,"lon":2.456557},{"lat":49.207901,"lon":2.456396},{"lat":49.208664,"lon":2.456123},{"lat":49.209038,"lon":2.45597},{"lat":49.209499,"lon":2.455761},{"lat":49.210037,"lon":2.455485},{"lat":49.210335,"lon":2.455318},{"lat":49.211216,"lon":2.454795},{"lat":49.220474,"lon":2.449384},{"lat":49.230633,"lon":2.443429},{"lat":49.232063,"lon":2.44263},{"lat":49.232491,"lon":2.44242},{"lat":49.232738,"lon":2.442306},{"lat":49.232922,"lon":2.442231},{"lat":49.233257,"lon":2.442114},{"lat":49.233658,"lon":2.441998},{"lat":49.234089,"lon":2.441915},{"lat":49.234287,"lon":2.44189},{"lat":49.234631,"lon":2.441866},{"lat":49.234852,"lon":2.441863},{"lat":49.235313,"lon":2.441889},{"lat":49.235516,"lon":2.441914},{"lat":49.236023,"lon":2.442009},{"lat":49.2365,"lon":2.442146},{"lat":49.236835,"lon":2.442276},{"lat":49.237316,"lon":2.442508},{"lat":49.237724,"lon":2.442747},{"lat":49.238079,"lon":2.442988},{"lat":49.238403,"lon":2.443243},{"lat":49.238697,"lon":2.443491},{"lat":49.24213,"lon":2.446625},{"lat":49.24316,"lon":2.447545},{"lat":49.244446,"lon":2.448642},{"lat":49.244991,"lon":2.44909},{"lat":49.246498,"lon":2.4503},{"lat":49.246944,"lon":2.450663},{"lat":49.247486,"lon":2.451121},{"lat":49.248348,"lon":2.451884},{"lat":49.249912,"lon":2.453321},{"lat":49.250351,"lon":2.453744},{"lat":49.251362,"lon":2.454751},{"lat":49.251965,"lon":2.455369},{"lat":49.252617,"lon":2.456069},{"lat":49.254799,"lon":2.458553},{"lat":49.256981,"lon":2.46106},{"lat":49.259068,"lon":2.463427},{"lat":49.262409,"lon":2.467147},{"lat":49.263844,"lon":2.468769},{"lat":49.263844,"lon":2.468769},{"lat":49.264633,"lon":2.469666},{"lat":49.265415,"lon":2.470538},{"lat":49.266003,"lon":2.471161},{"lat":49.26614,"lon":2.4713},{"lat":49.266396,"lon":2.471538},{"lat":49.266712,"lon":2.471801},{"lat":49.266922,"lon":2.471951},{"lat":49.267136,"lon":2.47209},{"lat":49.267361,"lon":2.47222},{"lat":49.267803,"lon":2.472439},{"lat":49.268467,"lon":2.472716},{"lat":49.269093,"lon":2.472955},{"lat":49.269627,"lon":2.473176},{"lat":49.26997,"lon":2.473331},{"lat":49.27042,"lon":2.473553},{"lat":49.27071,"lon":2.473711},{"lat":49.271042,"lon":2.473905},{"lat":49.271648,"lon":2.474298},{"lat":49.271988,"lon":2.47454},{"lat":49.272385,"lon":2.474834},{"lat":49.273056,"lon":2.47537},{"lat":49.273537,"lon":2.475787},{"lat":49.27401,"lon":2.476224},{"lat":49.274246,"lon":2.476454},{"lat":49.274765,"lon":2.476989},{"lat":49.275059,"lon":2.477309},{"lat":49.275475,"lon":2.477784},{"lat":49.275738,"lon":2.4781},{"lat":49.27634,"lon":2.478876},{"lat":49.276733,"lon":2.479416},{"lat":49.277241,"lon":2.480165},{"lat":49.277645,"lon":2.48081},{"lat":49.277946,"lon":2.481313},{"lat":49.278381,"lon":2.482092},{"lat":49.289665,"lon":2.502974},{"lat":49.290192,"lon":2.503961},{"lat":49.290722,"lon":2.504925},{"lat":49.291122,"lon":2.505676},{"lat":49.291546,"lon":2.506523},{"lat":49.292183,"lon":2.507873},{"lat":49.292274,"lon":2.508083},{"lat":49.292786,"lon":2.50916},{"lat":49.293129,"lon":2.509919},{"lat":49.293533,"lon":2.51075},{"lat":49.294353,"lon":2.512486},{"lat":49.29475,"lon":2.513353},{"lat":49.295551,"lon":2.515056},{"lat":49.297218,"lon":2.518565},{"lat":49.298679,"lon":2.521679},{"lat":49.298939,"lon":2.522275},{"lat":49.29932,"lon":2.523245},{"lat":49.299583,"lon":2.524004},{"lat":49.299824,"lon":2.524742},{"lat":49.299969,"lon":2.52524},{"lat":49.30019,"lon":2.526057},{"lat":49.300259,"lon":2.52635},{"lat":49.300369,"lon":2.526913},{"lat":49.300449,"lon":2.527366},{"lat":49.300568,"lon":2.528145},{"lat":49.300674,"lon":2.529071},{"lat":49.301258,"lon":2.534284},{"lat":49.301403,"lon":2.535372},{"lat":49.301506,"lon":2.535996},{"lat":49.301598,"lon":2.536492},{"lat":49.301796,"lon":2.537349},{"lat":49.302067,"lon":2.538404},{"lat":49.302761,"lon":2.540987},{"lat":49.302986,"lon":2.541906},{"lat":49.303196,"lon":2.542875},{"lat":49.303337,"lon":2.543631},{"lat":49.303448,"lon":2.544271},{"lat":49.303585,"lon":2.545178},{"lat":49.303738,"lon":2.546444},{"lat":49.30381,"lon":2.547149},{"lat":49.307407,"lon":2.583822},{"lat":49.307869,"lon":2.58843},{"lat":49.308575,"lon":2.595678},{"lat":49.308685,"lon":2.596727},{"lat":49.308865,"lon":2.598028},{"lat":49.309036,"lon":2.599056},{"lat":49.309231,"lon":2.600074},{"lat":49.309525,"lon":2.601374},{"lat":49.309673,"lon":2.601961},{"lat":49.309902,"lon":2.602802},{"lat":49.310024,"lon":2.603226},{"lat":49.310417,"lon":2.604461},{"lat":49.310776,"lon":2.605455},{"lat":49.310982,"lon":2.605974},{"lat":49.311485,"lon":2.607165},{"lat":49.311813,"lon":2.607894},{"lat":49.312195,"lon":2.608679},{"lat":49.312584,"lon":2.609416},{"lat":49.313049,"lon":2.610256},{"lat":49.31358,"lon":2.611143},{"lat":49.31403,"lon":2.611828},{"lat":49.315243,"lon":2.61351},{"lat":49.325199,"lon":2.62701},{"lat":49.325722,"lon":2.627732},{"lat":49.325981,"lon":2.628105},{"lat":49.326481,"lon":2.628873},{"lat":49.326962,"lon":2.629668},{"lat":49.327492,"lon":2.630616},{"lat":49.327904,"lon":2.631419},{"lat":49.328354,"lon":2.632371},{"lat":49.328526,"lon":2.632756},{"lat":49.328835,"lon":2.633488},{"lat":49.329155,"lon":2.634284},{"lat":49.329407,"lon":2.634979},{"lat":49.32967,"lon":2.635749},{"lat":49.329922,"lon":2.636527},{"lat":49.330246,"lon":2.637662},{"lat":49.330544,"lon":2.638832},{"lat":49.330788,"lon":2.639928},{"lat":49.330906,"lon":2.640526},{"lat":49.331047,"lon":2.641323},{"lat":49.331158,"lon":2.641989},{"lat":49.337315,"lon":2.682753},{"lat":49.342789,"lon":2.719045},{"lat":49.342831,"lon":2.719388},{"lat":49.34288,"lon":2.719881},{"lat":49.343006,"lon":2.720831},{"lat":49.343056,"lon":2.721473},{"lat":49.34306,"lon":2.721905},{"lat":49.343029,"lon":2.722366},{"lat":49.342995,"lon":2.722653},{"lat":49.342937,"lon":2.722974},{"lat":49.34285,"lon":2.723346},{"lat":49.342762,"lon":2.723646},{"lat":49.342674,"lon":2.723887},{"lat":49.342529,"lon":2.724214},{"lat":49.342373,"lon":2.724511},{"lat":49.342194,"lon":2.724785},{"lat":49.342007,"lon":2.725033},{"lat":49.341774,"lon":2.725277},{"lat":49.341652,"lon":2.725385},{"lat":49.341446,"lon":2.725538},{"lat":49.341335,"lon":2.725608},{"lat":49.341122,"lon":2.725718},{"lat":49.340939,"lon":2.725789},{"lat":49.340824,"lon":2.725821},{"lat":49.340656,"lon":2.725856},{"lat":49.340485,"lon":2.725875},{"lat":49.340252,"lon":2.725884},{"lat":49.337502,"lon":2.725827},{"lat":49.337154,"lon":2.725832},{"lat":49.336929,"lon":2.725857},{"lat":49.336628,"lon":2.725923},{"lat":49.336338,"lon":2.72602},{"lat":49.336208,"lon":2.726074},{"lat":49.336063,"lon":2.726147},{"lat":49.335907,"lon":2.726229},{"lat":49.335697,"lon":2.726355},{"lat":49.335403,"lon":2.726562},{"lat":49.335201,"lon":2.726738},{"lat":49.335014,"lon":2.726915},{"lat":49.331173,"lon":2.730956},{"lat":49.330605,"lon":2.731604},{"lat":49.330242,"lon":2.73204},{"lat":49.32983,"lon":2.732561},{"lat":49.327839,"lon":2.735121},{"lat":49.327374,"lon":2.735711},{"lat":49.327072,"lon":2.736072},{"lat":49.326748,"lon":2.736447},{"lat":49.326324,"lon":2.73691},{"lat":49.325825,"lon":2.737414},{"lat":49.325432,"lon":2.73779},{"lat":49.32317,"lon":2.739883},{"lat":49.322796,"lon":2.740257},{"lat":49.322643,"lon":2.740426},{"lat":49.322453,"lon":2.74065},{"lat":49.322212,"lon":2.740956},{"lat":49.321976,"lon":2.741285},{"lat":49.321781,"lon":2.741578},{"lat":49.321583,"lon":2.741904},{"lat":49.321308,"lon":2.742404},{"lat":49.321171,"lon":2.742668},{"lat":49.320969,"lon":2.743107},{"lat":49.320789,"lon":2.743541},{"lat":49.320095,"lon":2.745376},{"lat":49.313839,"lon":2.762121},{"lat":49.31097,"lon":2.769776},{"lat":49.310638,"lon":2.770639},{"lat":49.310345,"lon":2.771305},{"lat":49.310181,"lon":2.771646},{"lat":49.309895,"lon":2.77219},{"lat":49.309757,"lon":2.772434},{"lat":49.309425,"lon":2.772978},{"lat":49.309036,"lon":2.773551},{"lat":49.305698,"lon":2.778355},{"lat":49.305233,"lon":2.779041},{"lat":49.304913,"lon":2.779553},{"lat":49.304668,"lon":2.779992},{"lat":49.30455,"lon":2.780219},{"lat":49.304276,"lon":2.780768},{"lat":49.300125,"lon":2.789848},{"lat":49.294983,"lon":2.801068},{"lat":49.29451,"lon":2.802131},{"lat":49.294239,"lon":2.802807},{"lat":49.293991,"lon":2.803519},{"lat":49.293903,"lon":2.803814},{"lat":49.293716,"lon":2.804486},{"lat":49.293606,"lon":2.804934},{"lat":49.293442,"lon":2.805715},{"lat":49.29282,"lon":2.80919},{"lat":49.29266,"lon":2.809924},{"lat":49.292561,"lon":2.810322},{"lat":49.29245,"lon":2.810714},{"lat":49.292252,"lon":2.811372},{"lat":49.292061,"lon":2.811934},{"lat":49.289707,"lon":2.818825},{"lat":49.289505,"lon":2.819479},{"lat":49.289379,"lon":2.819937},{"lat":49.289181,"lon":2.820787},{"lat":49.289116,"lon":2.821113},{"lat":49.289013,"lon":2.821699},{"lat":49.28894,"lon":2.822197},{"lat":49.288872,"lon":2.822711},{"lat":49.287254,"lon":2.836462},{"lat":49.287132,"lon":2.837318},{"lat":49.287037,"lon":2.837869},{"lat":49.286884,"lon":2.838591},{"lat":49.286724,"lon":2.839236},{"lat":49.286648,"lon":2.839523},{"lat":49.286457,"lon":2.840146},{"lat":49.286339,"lon":2.840487},{"lat":49.286076,"lon":2.8412},{"lat":49.285862,"lon":2.841713},{"lat":49.285606,"lon":2.842269},{"lat":49.285343,"lon":2.842777},{"lat":49.285099,"lon":2.843213},{"lat":49.284832,"lon":2.843648},{"lat":49.284664,"lon":2.843897},{"lat":49.284359,"lon":2.844328},{"lat":49.284073,"lon":2.844699},{"lat":49.283684,"lon":2.845143},{"lat":49.283436,"lon":2.845395},{"lat":49.283138,"lon":2.84567},{"lat":49.28278,"lon":2.845959},{"lat":49.282326,"lon":2.846286},{"lat":49.273304,"lon":2.85246},{"lat":49.272919,"lon":2.852702},{"lat":49.272598,"lon":2.852873},{"lat":49.272339,"lon":2.852983},{"lat":49.272064,"lon":2.85308},{"lat":49.271774,"lon":2.853157},{"lat":49.271629,"lon":2.853187},{"lat":49.271484,"lon":2.853205},{"lat":49.271076,"lon":2.853233},{"lat":49.270752,"lon":2.853226},{"lat":49.270321,"lon":2.853181},{"lat":49.267765,"lon":2.852843},{"lat":49.267414,"lon":2.852815},{"lat":49.267246,"lon":2.852812},{"lat":49.267117,"lon":2.852817},{"lat":49.266979,"lon":2.852829},{"lat":49.266678,"lon":2.852877},{"lat":49.266445,"lon":2.852937},{"lat":49.2663,"lon":2.852987},{"lat":49.265991,"lon":2.853106},{"lat":49.264793,"lon":2.853672},{"lat":49.264477,"lon":2.853793},{"lat":49.264259,"lon":2.853858},{"lat":49.264061,"lon":2.853902},{"lat":49.263748,"lon":2.853937},{"lat":49.263573,"lon":2.853945},{"lat":49.263397,"lon":2.85394},{"lat":49.262966,"lon":2.853904},{"lat":49.2621,"lon":2.853788},{"lat":49.261757,"lon":2.853761},{"lat":49.261574,"lon":2.85376},{"lat":49.261234,"lon":2.853787},{"lat":49.261078,"lon":2.853815},{"lat":49.260841,"lon":2.85387},{"lat":49.260639,"lon":2.853935},{"lat":49.260303,"lon":2.854076},{"lat":49.260017,"lon":2.85423},{"lat":49.259842,"lon":2.854341},{"lat":49.259529,"lon":2.854577},{"lat":49.259205,"lon":2.854873},{"lat":49.259056,"lon":2.85503},{"lat":49.258873,"lon":2.855237},{"lat":49.258656,"lon":2.855513},{"lat":49.258095,"lon":2.856313},{"lat":49.257805,"lon":2.856678},{"lat":49.257481,"lon":2.857058},{"lat":49.257332,"lon":2.857214},{"lat":49.257187,"lon":2.857347},{"lat":49.257023,"lon":2.857484},{"lat":49.256752,"lon":2.857682},{"lat":49.256428,"lon":2.857877},{"lat":49.256294,"lon":2.857942},{"lat":49.255951,"lon":2.858089},{"lat":49.255692,"lon":2.858171},{"lat":49.255325,"lon":2.858237},{"lat":49.255032,"lon":2.858263},{"lat":49.25367,"lon":2.858231},{"lat":49.253471,"lon":2.858233},{"lat":49.253262,"lon":2.858244},{"lat":49.253075,"lon":2.858262},{"lat":49.252926,"lon":2.858285},{"lat":49.252728,"lon":2.858321},{"lat":49.252369,"lon":2.858422},{"lat":49.252098,"lon":2.858516},{"lat":49.251316,"lon":2.858816},{"lat":49.250877,"lon":2.858962},{"lat":49.250576,"lon":2.859034},{"lat":49.250389,"lon":2.859067},{"lat":49.250072,"lon":2.859101},{"lat":49.249912,"lon":2.859105},{"lat":49.249599,"lon":2.859093},{"lat":49.249348,"lon":2.85906},{"lat":49.248932,"lon":2.858975},{"lat":49.248085,"lon":2.858755},{"lat":49.247593,"lon":2.85865},{"lat":49.247307,"lon":2.858612},{"lat":49.247021,"lon":2.858597},{"lat":49.246666,"lon":2.858609},{"lat":49.246376,"lon":2.858643},{"lat":49.246204,"lon":2.858674},{"lat":49.245979,"lon":2.858722},{"lat":49.244999,"lon":2.85898},{"lat":49.244667,"lon":2.859057},{"lat":49.244492,"lon":2.859089},{"lat":49.244335,"lon":2.859111},{"lat":49.244164,"lon":2.859123},{"lat":49.243828,"lon":2.859131},{"lat":49.243652,"lon":2.859124},{"lat":49.24345,"lon":2.859105},{"lat":49.243275,"lon":2.859076},{"lat":49.24297,"lon":2.859005},{"lat":49.242664,"lon":2.858906},{"lat":49.242474,"lon":2.858827},{"lat":49.242115,"lon":2.858649},{"lat":49.241558,"lon":2.858311},{"lat":49.240952,"lon":2.857929},{"lat":49.24078,"lon":2.857826},{"lat":49.240433,"lon":2.857648},{"lat":49.240204,"lon":2.857546},{"lat":49.239857,"lon":2.857422},{"lat":49.239597,"lon":2.857356},{"lat":49.239334,"lon":2.857307},{"lat":49.239155,"lon":2.857287},{"lat":49.238831,"lon":2.857273},{"lat":49.238537,"lon":2.857289},{"lat":49.238216,"lon":2.857328},{"lat":49.234623,"lon":2.857969},{"lat":49.234066,"lon":2.858059},{"lat":49.233845,"lon":2.858085},{"lat":49.233612,"lon":2.858108},{"lat":49.233204,"lon":2.858118},{"lat":49.23299,"lon":2.858114},{"lat":49.232601,"lon":2.858082},{"lat":49.232372,"lon":2.858051},{"lat":49.2318,"lon":2.857958},{"lat":49.230019,"lon":2.857646},{"lat":49.229813,"lon":2.857603},{"lat":49.229465,"lon":2.85751},{"lat":49.229088,"lon":2.857387},{"lat":49.225327,"lon":2.855973},{"lat":49.224602,"lon":2.855681},{"lat":49.224426,"lon":2.855599},{"lat":49.224007,"lon":2.855381},{"lat":49.223583,"lon":2.855126},{"lat":49.223392,"lon":2.855001},{"lat":49.223083,"lon":2.854776},{"lat":49.222832,"lon":2.85458},{"lat":49.222561,"lon":2.854348},{"lat":49.21983,"lon":2.851877},{"lat":49.219364,"lon":2.851468},{"lat":49.219139,"lon":2.851284},{"lat":49.218803,"lon":2.851034},{"lat":49.218517,"lon":2.850842},{"lat":49.218216,"lon":2.850658},{"lat":49.217949,"lon":2.850514},{"lat":49.217701,"lon":2.850391},{"lat":49.208256,"lon":2.84588},{"lat":49.207767,"lon":2.845634},{"lat":49.207294,"lon":2.845367},{"lat":49.206684,"lon":2.844971},{"lat":49.206047,"lon":2.844541},{"lat":49.205612,"lon":2.844228},{"lat":49.205429,"lon":2.84408},{"lat":49.205212,"lon":2.843891},{"lat":49.20504,"lon":2.843715},{"lat":49.204823,"lon":2.843476},{"lat":49.204601,"lon":2.843204},{"lat":49.204205,"lon":2.842678},{"lat":49.202782,"lon":2.840757},{"lat":49.20245,"lon":2.840281},{"lat":49.201725,"lon":2.839215},{"lat":49.201382,"lon":2.838737},{"lat":49.200333,"lon":2.837321},{"lat":49.199947,"lon":2.836855},{"lat":49.199051,"lon":2.8358},{"lat":49.198833,"lon":2.835554},{"lat":49.19862,"lon":2.835283},{"lat":49.200977,"lon":2.838472},{"lat":49.200977,"lon":2.838472},{"lat":49.227097,"lon":2.873762},{"lat":49.22794,"lon":2.874913},{"lat":49.228188,"lon":2.875285},{"lat":49.228382,"lon":2.875592},{"lat":49.228718,"lon":2.876163},{"lat":49.228912,"lon":2.876526},{"lat":49.229069,"lon":2.876837},{"lat":49.22934,"lon":2.877416},{"lat":49.22953,"lon":2.877857},{"lat":49.22966,"lon":2.878174},{"lat":49.2299,"lon":2.878815},{"lat":49.230019,"lon":2.879148},{"lat":49.23024,"lon":2.879859},{"lat":49.230434,"lon":2.880566},{"lat":49.230576,"lon":2.881162},{"lat":49.230717,"lon":2.881877},{"lat":49.230804,"lon":2.88239},{"lat":49.230904,"lon":2.88316},{"lat":49.230953,"lon":2.883637},{"lat":49.230995,"lon":2.884203},{"lat":49.231106,"lon":2.88649}],"IDFM:shp_2_70":[{"lat":49.231071,"lon":2.886496},{"lat":49.230995,"lon":2.884792},{"lat":49.230942,"lon":2.88389},{"lat":49.230904,"lon":2.883488},{"lat":49.230827,"lon":2.8828},{"lat":49.23077,"lon":2.882399},{"lat":49.230633,"lon":2.881603},{"lat":49.230541,"lon":2.881177},{"lat":49.230404,"lon":2.880582},{"lat":49.230209,"lon":2.879878},{"lat":49.230072,"lon":2.879424},{"lat":49.22987,"lon":2.878837},{"lat":49.229752,"lon":2.878516},{"lat":49.229504,"lon":2.877884},{"lat":49.229313,"lon":2.877443},{"lat":49.229038,"lon":2.876864},{"lat":49.228691,"lon":2.876196},{"lat":49.228359,"lon":2.875628},{"lat":49.228165,"lon":2.875322},{"lat":49.227913,"lon":2.874948},{"lat":49.227074,"lon":2.8738},{"lat":49.200962,"lon":2.838515},{"lat":49.200962,"lon":2.838515},{"lat":49.1987,"lon":2.835459},{"lat":49.198891,"lon":2.835696},{"lat":49.199379,"lon":2.836241},{"lat":49.199642,"lon":2.836551},{"lat":49.199947,"lon":2.836855},{"lat":49.200333,"lon":2.837321},{"lat":49.201382,"lon":2.838737},{"lat":49.201725,"lon":2.839215},{"lat":49.20245,"lon":2.840281},{"lat":49.202782,"lon":2.840757},{"lat":49.204205,"lon":2.842678},{"lat":49.204601,"lon":2.843204},{"lat":49.204823,"lon":2.843476},{"lat":49.20504,"lon":2.843715},{"lat":49.205212,"lon":2.843891},{"lat":49.205429,"lon":2.84408},{"lat":49.205612,"lon":2.844228},{"lat":49.206047,"lon":2.844541},{"lat":49.206684,"lon":2.844971},{"lat":49.207294,"lon":2.845367},{"lat":49.207767,"lon":2.845634},{"lat":49.208256,"lon":2.84588},{"lat":49.217701,"lon":2.850391},{"lat":49.217949,"lon":2.850514},{"lat":49.218216,"lon":2.850658},{"lat":49.218517,"lon":2.850842},{"lat":49.218803,"lon":2.851034},{"lat":49.219139,"lon":2.851284},{"lat":49.219364,"lon":2.851468},{"lat":49.21983,"lon":2.851877},{"lat":49.222561,"lon":2.854348},{"lat":49.222832,"lon":2.85458},{"lat":49.223083,"lon":2.854776},{"lat":49.223392,"lon":2.855001},{"lat":49.223583,"lon":2.855126},{"lat":49.224007,"lon":2.855381},{"lat":49.224426,"lon":2.855599},{"lat":49.224602,"lon":2.855681},{"lat":49.225327,"lon":2.855973},{"lat":49.229088,"lon":2.857387},{"lat":49.229465,"lon":2.85751},{"lat":49.229813,"lon":2.857603},{"lat":49.230019,"lon":2.857646},{"lat":49.2318,"lon":2.857958},{"lat":49.232372,"lon":2.858051},{"lat":49.232601,"lon":2.858082},{"lat":49.23299,"lon":2.858114},{"lat":49.233204,"lon":2.858118},{"lat":49.233612,"lon":2.858108},{"lat":49.233845,"lon":2.858085},{"lat":49.234066,"lon":2.858059},{"lat":49.234623,"lon":2.857969},{"lat":49.238216,"lon":2.857328},{"lat":49.238537,"lon":2.857289},{"lat":49.238831,"lon":2.857273},{"lat":49.239155,"lon":2.857287},{"lat":49.239334,"lon":2.857307},{"lat":49.239597,"lon":2.857356},{"lat":49.239857,"lon":2.857422},{"lat":49.240204,"lon":2.857546},{"lat":49.240433,"lon":2.857648},{"lat":49.24078,"lon":2.857826},{"lat":49.240952,"lon":2.857929},{"lat":49.241558,"lon":2.858311},{"lat":49.242115,"lon":2.858649},{"lat":49.242474,"lon":2.858827},{"lat":49.242664,"lon":2.858906},{"lat":49.24297,"lon":2.859005},{"lat":49.243275,"lon":2.859076},{"lat":49.24345,"lon":2.859105},{"lat":49.243652,"lon":2.859124},{"lat":49.243828,"lon":2.859131},{"lat":49.244164,"lon":2.859123},{"lat":49.244335,"lon":2.859111},{"lat":49.244492,"lon":2.859089},{"lat":49.244667,"lon":2.859057},{"lat":49.244999,"lon":2.85898},{"lat":49.245979,"lon":2.858722},{"lat":49.246204,"lon":2.858674},{"lat":49.246376,"lon":2.858643},{"lat":49.246666,"lon":2.858609},{"lat":49.247021,"lon":2.858597},{"lat":49.247307,"lon":2.858612},{"lat":49.247593,"lon":2.85865},{"lat":49.248085,"lon":2.858755},{"lat":49.248932,"lon":2.858975},{"lat":49.249348,"lon":2.85906},{"lat":49.249599,"lon":2.859093},{"lat":49.249912,"lon":2.859105},{"lat":49.250072,"lon":2.859101},{"lat":49.250389,"lon":2.859067},{"lat":49.250576,"lon":2.859034},{"lat":49.250877,"lon":2.858962},{"lat":49.251316,"lon":2.858816},{"lat":49.252098,"lon":2.858516},{"lat":49.252369,"lon":2.858422},{"lat":49.252728,"lon":2.858321},{"lat":49.252926,"lon":2.858285},{"lat":49.253075,"lon":2.858262},{"lat":49.253262,"lon":2.858244},{"lat":49.253471,"lon":2.858233},{"lat":49.25367,"lon":2.858231},{"lat":49.255032,"lon":2.858263},{"lat":49.255325,"lon":2.858237},{"lat":49.255692,"lon":2.858171},{"lat":49.255951,"lon":2.858089},{"lat":49.256294,"lon":2.857942},{"lat":49.256428,"lon":2.857877},{"lat":49.256752,"lon":2.857682},{"lat":49.257023,"lon":2.857484},{"lat":49.257187,"lon":2.857347},{"lat":49.257332,"lon":2.857214},{"lat":49.257481,"lon":2.857058},{"lat":49.257805,"lon":2.856678},{"lat":49.258095,"lon":2.856313},{"lat":49.258656,"lon":2.855513},{"lat":49.258873,"lon":2.855237},{"lat":49.259056,"lon":2.85503},{"lat":49.259205,"lon":2.854873},{"lat":49.259529,"lon":2.854577},{"lat":49.259842,"lon":2.854341},{"lat":49.260017,"lon":2.85423},{"lat":49.260303,"lon":2.854076},{"lat":49.260639,"lon":2.853935},{"lat":49.260841,"lon":2.85387},{"lat":49.261078,"lon":2.853815},{"lat":49.261234,"lon":2.853787},{"lat":49.261574,"lon":2.85376},{"lat":49.261757,"lon":2.853761},{"lat":49.2621,"lon":2.853788},{"lat":49.262966,"lon":2.853904},{"lat":49.263397,"lon":2.85394},{"lat":49.263573,"lon":2.853945},{"lat":49.263748,"lon":2.853937},{"lat":49.264061,"lon":2.853902},{"lat":49.264259,"lon":2.853858},{"lat":49.264477,"lon":2.853793},{"lat":49.264793,"lon":2.853672},{"lat":49.265991,"lon":2.853106},{"lat":49.2663,"lon":2.852987},{"lat":49.266445,"lon":2.852937},{"lat":49.266678,"lon":2.852877},{"lat":49.266979,"lon":2.852829},{"lat":49.267117,"lon":2.852817},{"lat":49.267246,"lon":2.852812},{"lat":49.267414,"lon":2.852815},{"lat":49.267765,"lon":2.852843},{"lat":49.270321,"lon":2.853181},{"lat":49.270752,"lon":2.853226},{"lat":49.271076,"lon":2.853233},{"lat":49.271484,"lon":2.853205},{"lat":49.271629,"lon":2.853187},{"lat":49.271774,"lon":2.853157},{"lat":49.272064,"lon":2.85308},{"lat":49.272339,"lon":2.852983},{"lat":49.272598,"lon":2.852873},{"lat":49.272919,"lon":2.852702},{"lat":49.273304,"lon":2.85246},{"lat":49.282326,"lon":2.846286},{"lat":49.28278,"lon":2.845959},{"lat":49.283138,"lon":2.84567},{"lat":49.283436,"lon":2.845395},{"lat":49.283684,"lon":2.845143},{"lat":49.284073,"lon":2.844699},{"lat":49.284359,"lon":2.844328},{"lat":49.284664,"lon":2.843897},{"lat":49.284832,"lon":2.843648},{"lat":49.285099,"lon":2.843213},{"lat":49.285343,"lon":2.842777},{"lat":49.285606,"lon":2.842269},{"lat":49.285862,"lon":2.841713},{"lat":49.286076,"lon":2.8412},{"lat":49.286339,"lon":2.840487},{"lat":49.286457,"lon":2.840146},{"lat":49.286648,"lon":2.839523},{"lat":49.286724,"lon":2.839236},{"lat":49.286884,"lon":2.838591},{"lat":49.287037,"lon":2.837869},{"lat":49.287132,"lon":2.837318},{"lat":49.287254,"lon":2.836462},{"lat":49.288872,"lon":2.822711},{"lat":49.28894,"lon":2.822197},{"lat":49.289013,"lon":2.821699},{"lat":49.289116,"lon":2.821113},{"lat":49.289181,"lon":2.820787},{"lat":49.289379,"lon":2.819937},{"lat":49.289505,"lon":2.819479},{"lat":49.289707,"lon":2.818825},{"lat":49.292061,"lon":2.811934},{"lat":49.292252,"lon":2.811372},{"lat":49.29245,"lon":2.810714},{"lat":49.292561,"lon":2.810322},{"lat":49.29266,"lon":2.809924},{"lat":49.29282,"lon":2.80919},{"lat":49.293442,"lon":2.805715},{"lat":49.293606,"lon":2.804934},{"lat":49.293716,"lon":2.804486},{"lat":49.293903,"lon":2.803814},{"lat":49.293991,"lon":2.803519},{"lat":49.294239,"lon":2.802807},{"lat":49.29451,"lon":2.802131},{"lat":49.294983,"lon":2.801068},{"lat":49.300125,"lon":2.789848},{"lat":49.304276,"lon":2.780768},{"lat":49.30455,"lon":2.780219},{"lat":49.304668,"lon":2.779992},{"lat":49.304913,"lon":2.779553},{"lat":49.305233,"lon":2.779041},{"lat":49.305698,"lon":2.778355},{"lat":49.309036,"lon":2.773551},{"lat":49.309425,"lon":2.772978},{"lat":49.309757,"lon":2.772434},{"lat":49.309895,"lon":2.77219},{"lat":49.310181,"lon":2.771646},{"lat":49.310345,"lon":2.771305},{"lat":49.310638,"lon":2.770639},{"lat":49.31097,"lon":2.769776},{"lat":49.313839,"lon":2.762121},{"lat":49.320095,"lon":2.745376},{"lat":49.320789,"lon":2.743541},{"lat":49.320969,"lon":2.743107},{"lat":49.321171,"lon":2.742668},{"lat":49.321308,"lon":2.742404},{"lat":49.321583,"lon":2.741904},{"lat":49.321781,"lon":2.741578},{"lat":49.321976,"lon":2.741285},{"lat":49.322212,"lon":2.740956},{"lat":49.322453,"lon":2.74065},{"lat":49.322643,"lon":2.740426},{"lat":49.322796,"lon":2.740257},{"lat":49.32317,"lon":2.739883},{"lat":49.325432,"lon":2.73779},{"lat":49.325825,"lon":2.737414},{"lat":49.326324,"lon":2.73691},{"lat":49.326748,"lon":2.736447},{"lat":49.327072,"lon":2.736072},{"lat":49.327374,"lon":2.735711},{"lat":49.327839,"lon":2.735121},{"lat":49.32983,"lon":2.732561},{"lat":49.330242,"lon":2.73204},{"lat":49.330605,"lon":2.731604},{"lat":49.331173,"lon":2.730956},{"lat":49.335014,"lon":2.726915},{"lat":49.335201,"lon":2.726738},{"lat":49.335403,"lon":2.726562},{"lat":49.335697,"lon":2.726355},{"lat":49.335907,"lon":2.726229},{"lat":49.336063,"lon":2.726147},{"lat":49.336208,"lon":2.726074},{"lat":49.336338,"lon":2.72602},{"lat":49.336628,"lon":2.725923},{"lat":49.336929,"lon":2.725857},{"lat":49.337154,"lon":2.725832},{"lat":49.337502,"lon":2.725827},{"lat":49.340252,"lon":2.725884},{"lat":49.340485,"lon":2.725875},{"lat":49.340656,"lon":2.725856},{"lat":49.340824,"lon":2.725821},{"lat":49.340939,"lon":2.725789},{"lat":49.341122,"lon":2.725718},{"lat":49.341335,"lon":2.725608},{"lat":49.341446,"lon":2.725538},{"lat":49.341652,"lon":2.725385},{"lat":49.341774,"lon":2.725277},{"lat":49.342007,"lon":2.725033},{"lat":49.342194,"lon":2.724785},{"lat":49.342373,"lon":2.724511},{"lat":49.342529,"lon":2.724214},{"lat":49.342674,"lon":2.723887},{"lat":49.342762,"lon":2.723646},{"lat":49.34285,"lon":2.723346},{"lat":49.342937,"lon":2.722974},{"lat":49.342995,"lon":2.722653},{"lat":49.343029,"lon":2.722366},{"lat":49.34306,"lon":2.721905},{"lat":49.343056,"lon":2.721473},{"lat":49.343006,"lon":2.720831},{"lat":49.342934,"lon":2.720244},{"lat":49.337284,"lon":2.682766},{"lat":49.331123,"lon":2.641997},{"lat":49.331017,"lon":2.64135},{"lat":49.330875,"lon":2.640539},{"lat":49.330757,"lon":2.639945},{"lat":49.330513,"lon":2.638849},{"lat":49.330215,"lon":2.637682},{"lat":49.330055,"lon":2.637118},{"lat":49.329769,"lon":2.636168},{"lat":49.32938,"lon":2.635002},{"lat":49.329121,"lon":2.634308},{"lat":49.328804,"lon":2.633506},{"lat":49.328503,"lon":2.632791},{"lat":49.328327,"lon":2.632399},{"lat":49.327877,"lon":2.631447},{"lat":49.327461,"lon":2.630643},{"lat":49.327145,"lon":2.630062},{"lat":49.326939,"lon":2.629697},{"lat":49.326603,"lon":2.629138},{"lat":49.326183,"lon":2.628482},{"lat":49.325703,"lon":2.62777},{"lat":49.325184,"lon":2.627056},{"lat":49.315212,"lon":2.61354},{"lat":49.314571,"lon":2.612654},{"lat":49.313992,"lon":2.611837},{"lat":49.313557,"lon":2.611179},{"lat":49.313019,"lon":2.610282},{"lat":49.312561,"lon":2.609454},{"lat":49.312168,"lon":2.608712},{"lat":49.31179,"lon":2.607924},{"lat":49.311459,"lon":2.607187},{"lat":49.310959,"lon":2.606014},{"lat":49.310543,"lon":2.604928},{"lat":49.31039,"lon":2.604492},{"lat":49.309994,"lon":2.603246},{"lat":49.309872,"lon":2.602819},{"lat":49.309647,"lon":2.601989},{"lat":49.309498,"lon":2.6014},{"lat":49.30933,"lon":2.600686},{"lat":49.309082,"lon":2.599488},{"lat":49.308899,"lon":2.598469},{"lat":49.308693,"lon":2.597041},{"lat":49.30862,"lon":2.596451},{"lat":49.308426,"lon":2.59457},{"lat":49.308113,"lon":2.591255},{"lat":49.307838,"lon":2.588438},{"lat":49.307377,"lon":2.583831},{"lat":49.304718,"lon":2.556699},{"lat":49.303703,"lon":2.54645},{"lat":49.303619,"lon":2.545702},{"lat":49.303482,"lon":2.544711},{"lat":49.303307,"lon":2.543643},{"lat":49.303108,"lon":2.54263},{"lat":49.302952,"lon":2.541924},{"lat":49.302731,"lon":2.541024},{"lat":49.301868,"lon":2.537789},{"lat":49.301682,"lon":2.537032},{"lat":49.301582,"lon":2.536579},{"lat":49.301476,"lon":2.536027},{"lat":49.301418,"lon":2.53571},{"lat":49.301296,"lon":2.534857},{"lat":49.301178,"lon":2.53389},{"lat":49.300549,"lon":2.528278},{"lat":49.30051,"lon":2.527976},{"lat":49.300377,"lon":2.527149},{"lat":49.300282,"lon":2.526637},{"lat":49.300201,"lon":2.526259},{"lat":49.300102,"lon":2.525857},{"lat":49.299942,"lon":2.525258},{"lat":49.299793,"lon":2.524762},{"lat":49.299683,"lon":2.524409},{"lat":49.299313,"lon":2.523327},{"lat":49.298897,"lon":2.522266},{"lat":49.298649,"lon":2.5217},{"lat":49.297195,"lon":2.518596},{"lat":49.296017,"lon":2.516121},{"lat":49.295143,"lon":2.514275},{"lat":49.294323,"lon":2.512514},{"lat":49.293011,"lon":2.509752},{"lat":49.292747,"lon":2.509162},{"lat":49.292252,"lon":2.508122},{"lat":49.292145,"lon":2.50788},{"lat":49.291527,"lon":2.506565},{"lat":49.291237,"lon":2.505979},{"lat":49.290699,"lon":2.504968},{"lat":49.289623,"lon":2.502981},{"lat":49.289116,"lon":2.502053},{"lat":49.286575,"lon":2.497336},{"lat":49.278179,"lon":2.481801},{"lat":49.277924,"lon":2.481346},{"lat":49.277584,"lon":2.480782},{"lat":49.27721,"lon":2.480183},{"lat":49.27689,"lon":2.479708},{"lat":49.276516,"lon":2.479182},{"lat":49.276043,"lon":2.47855},{"lat":49.275711,"lon":2.478135},{"lat":49.275238,"lon":2.477573},{"lat":49.274738,"lon":2.477023},{"lat":49.274326,"lon":2.476589},{"lat":49.273727,"lon":2.476017},{"lat":49.273388,"lon":2.475709},{"lat":49.272877,"lon":2.475277},{"lat":49.272171,"lon":2.474729},{"lat":49.271748,"lon":2.474421},{"lat":49.271328,"lon":2.474141},{"lat":49.270988,"lon":2.473937},{"lat":49.270657,"lon":2.473751},{"lat":49.270245,"lon":2.473546},{"lat":49.269928,"lon":2.473399},{"lat":49.267803,"lon":2.472501},{"lat":49.267509,"lon":2.47236},{"lat":49.267288,"lon":2.472239},{"lat":49.267048,"lon":2.472094},{"lat":49.266808,"lon":2.471931},{"lat":49.266605,"lon":2.471776},{"lat":49.26643,"lon":2.471628},{"lat":49.266136,"lon":2.471354},{"lat":49.26569,"lon":2.470895},{"lat":49.26498,"lon":2.470122},{"lat":49.263828,"lon":2.468819},{"lat":49.263828,"lon":2.468819},{"lat":49.260742,"lon":2.465347},{"lat":49.259209,"lon":2.463645},{"lat":49.257813,"lon":2.462067},{"lat":49.253044,"lon":2.456601},{"lat":49.252491,"lon":2.455992},{"lat":49.251736,"lon":2.455193},{"lat":49.251213,"lon":2.454657},{"lat":49.250343,"lon":2.453792},{"lat":49.249378,"lon":2.452884},{"lat":49.248337,"lon":2.451929},{"lat":49.247902,"lon":2.451547},{"lat":49.247238,"lon":2.450994},{"lat":49.246773,"lon":2.45062},{"lat":49.245171,"lon":2.449391},{"lat":49.244526,"lon":2.448882},{"lat":49.243969,"lon":2.448432},{"lat":49.243042,"lon":2.447661},{"lat":49.24234,"lon":2.447064},{"lat":49.241539,"lon":2.446354},{"lat":49.24102,"lon":2.445891},{"lat":49.239468,"lon":2.444466},{"lat":49.239094,"lon":2.444151},{"lat":49.238644,"lon":2.443795},{"lat":49.238163,"lon":2.443455},{"lat":49.237785,"lon":2.443212},{"lat":49.237427,"lon":2.443004},{"lat":49.237053,"lon":2.442811},{"lat":49.236633,"lon":2.442626},{"lat":49.236427,"lon":2.442547},{"lat":49.236282,"lon":2.442499},{"lat":49.235928,"lon":2.442403},{"lat":49.235439,"lon":2.442293},{"lat":49.235176,"lon":2.442255},{"lat":49.234684,"lon":2.44222},{"lat":49.234478,"lon":2.442218},{"lat":49.234238,"lon":2.442228},{"lat":49.233719,"lon":2.442275},{"lat":49.233372,"lon":2.442333},{"lat":49.232918,"lon":2.442436},{"lat":49.232742,"lon":2.442489},{"lat":49.232426,"lon":2.442605},{"lat":49.23196,"lon":2.442804},{"lat":49.230694,"lon":2.443508},{"lat":49.229229,"lon":2.444357},{"lat":49.228531,"lon":2.444752},{"lat":49.228142,"lon":2.444963},{"lat":49.226971,"lon":2.445633},{"lat":49.210674,"lon":2.455167},{"lat":49.210224,"lon":2.455426},{"lat":49.209911,"lon":2.455592},{"lat":49.209435,"lon":2.455833},{"lat":49.208889,"lon":2.456076},{"lat":49.20853,"lon":2.456221},{"lat":49.207813,"lon":2.456478},{"lat":49.207119,"lon":2.456682},{"lat":49.206852,"lon":2.456751},{"lat":49.206367,"lon":2.456855},{"lat":49.205631,"lon":2.456975},{"lat":49.199558,"lon":2.457837},{"lat":49.199352,"lon":2.45786},{"lat":49.197033,"lon":2.458196},{"lat":49.191803,"lon":2.45894},{"lat":49.188995,"lon":2.459308},{"lat":49.187077,"lon":2.459571},{"lat":49.187077,"lon":2.459571},{"lat":49.186138,"lon":2.459704},{"lat":49.185535,"lon":2.459805},{"lat":49.185143,"lon":2.459888},{"lat":49.184361,"lon":2.46009},{"lat":49.18359,"lon":2.460341},{"lat":49.182167,"lon":2.460901},{"lat":49.175587,"lon":2.463592},{"lat":49.172638,"lon":2.464808},{"lat":49.170277,"lon":2.465769},{"lat":49.169971,"lon":2.465886},{"lat":49.16935,"lon":2.466148},{"lat":49.16711,"lon":2.467068},{"lat":49.160828,"lon":2.469633},{"lat":49.16016,"lon":2.469913},{"lat":49.159645,"lon":2.470144},{"lat":49.159267,"lon":2.470332},{"lat":49.15884,"lon":2.470566},{"lat":49.15847,"lon":2.470792},{"lat":49.158215,"lon":2.470963},{"lat":49.15781,"lon":2.47125},{"lat":49.157524,"lon":2.471471},{"lat":49.157238,"lon":2.471708},{"lat":49.156952,"lon":2.471957},{"lat":49.15649,"lon":2.472394},{"lat":49.155926,"lon":2.472976},{"lat":49.153904,"lon":2.475166},{"lat":49.152866,"lon":2.476278},{"lat":49.151505,"lon":2.477768},{"lat":49.14867,"lon":2.480842},{"lat":49.147537,"lon":2.482056},{"lat":49.147152,"lon":2.482448},{"lat":49.146648,"lon":2.482924},{"lat":49.14463,"lon":2.484719},{"lat":49.142345,"lon":2.486735},{"lat":49.141853,"lon":2.487159},{"lat":49.141068,"lon":2.487804},{"lat":49.140568,"lon":2.488237},{"lat":49.139523,"lon":2.489176},{"lat":49.13839,"lon":2.490182},{"lat":49.13839,"lon":2.490182},{"lat":49.137665,"lon":2.490834},{"lat":49.137054,"lon":2.491423},{"lat":49.136673,"lon":2.491819},{"lat":49.13623,"lon":2.492304},{"lat":49.135868,"lon":2.492724},{"lat":49.13549,"lon":2.493187},{"lat":49.135151,"lon":2.493621},{"lat":49.134747,"lon":2.494172},{"lat":49.134384,"lon":2.494687},{"lat":49.131695,"lon":2.498755},{"lat":49.129967,"lon":2.501402},{"lat":49.120224,"lon":2.516148},{"lat":49.119465,"lon":2.517357},{"lat":49.117359,"lon":2.520823},{"lat":49.117054,"lon":2.521311},{"lat":49.116673,"lon":2.521876},{"lat":49.116287,"lon":2.522408},{"lat":49.116039,"lon":2.522732},{"lat":49.1157,"lon":2.523143},{"lat":49.115246,"lon":2.523655},{"lat":49.114964,"lon":2.523949},{"lat":49.114483,"lon":2.524411},{"lat":49.114021,"lon":2.524816},{"lat":49.113682,"lon":2.525083},{"lat":49.113354,"lon":2.525317},{"lat":49.113186,"lon":2.525429},{"lat":49.112751,"lon":2.525689},{"lat":49.112495,"lon":2.525825},{"lat":49.112202,"lon":2.525959},{"lat":49.111851,"lon":2.526102},{"lat":49.111454,"lon":2.526237},{"lat":49.111137,"lon":2.526323},{"lat":49.110889,"lon":2.526379},{"lat":49.110523,"lon":2.526441},{"lat":49.110344,"lon":2.526462},{"lat":49.109951,"lon":2.526489},{"lat":49.109756,"lon":2.526492},{"lat":49.109245,"lon":2.526472},{"lat":49.099575,"lon":2.52556},{"lat":49.099575,"lon":2.52556},{"lat":49.098694,"lon":2.525469},{"lat":49.09412,"lon":2.525036},{"lat":49.091572,"lon":2.524738},{"lat":49.067513,"lon":2.52245},{"lat":49.067188,"lon":2.522412},{"lat":49.066685,"lon":2.522325},{"lat":49.066261,"lon":2.52222},{"lat":49.065853,"lon":2.522088},{"lat":49.065659,"lon":2.522011},{"lat":49.065277,"lon":2.521843},{"lat":49.064831,"lon":2.52161},{"lat":49.064564,"lon":2.52145},{"lat":49.064175,"lon":2.521192},{"lat":49.063885,"lon":2.520978},{"lat":49.06345,"lon":2.520619},{"lat":49.063114,"lon":2.520301},{"lat":49.062771,"lon":2.519944},{"lat":49.062561,"lon":2.519711},{"lat":49.06216,"lon":2.519218},{"lat":49.060879,"lon":2.51749},{"lat":49.052269,"lon":2.505782},{"lat":49.050568,"lon":2.503476},{"lat":49.050175,"lon":2.502953},{"lat":49.049576,"lon":2.502124},{"lat":49.043159,"lon":2.493412},{"lat":49.042023,"lon":2.491857},{"lat":49.041714,"lon":2.49142},{"lat":49.041203,"lon":2.49064},{"lat":49.032848,"lon":2.477463},{"lat":49.032482,"lon":2.476895},{"lat":49.028942,"lon":2.471298},{"lat":49.02747,"lon":2.468998},{"lat":49.027134,"lon":2.468494},{"lat":49.026188,"lon":2.467172},{"lat":49.026054,"lon":2.466972},{"lat":49.025436,"lon":2.466027},{"lat":49.022926,"lon":2.462059},{"lat":49.022926,"lon":2.462059},{"lat":49.022549,"lon":2.461472},{"lat":49.021881,"lon":2.460408},{"lat":49.020615,"lon":2.458231},{"lat":49.019932,"lon":2.457108},{"lat":49.012459,"lon":2.445342},{"lat":49.011288,"lon":2.443479},{"lat":49.009819,"lon":2.44118},{"lat":49.00293,"lon":2.430326},{"lat":49.001846,"lon":2.428636},{"lat":49.001118,"lon":2.42748},{"lat":49.000748,"lon":2.426908},{"lat":48.999325,"lon":2.424661},{"lat":48.998871,"lon":2.423953},{"lat":48.997803,"lon":2.422261},{"lat":48.997143,"lon":2.42126},{"lat":48.995541,"lon":2.418932},{"lat":48.993931,"lon":2.41646},{"lat":48.993931,"lon":2.41646},{"lat":48.993637,"lon":2.416007},{"lat":48.992805,"lon":2.414671},{"lat":48.992207,"lon":2.413668},{"lat":48.99136,"lon":2.412175},{"lat":48.990929,"lon":2.411453},{"lat":48.986393,"lon":2.404325},{"lat":48.986034,"lon":2.403788},{"lat":48.978729,"lon":2.39336},{"lat":48.977581,"lon":2.391736},{"lat":48.977169,"lon":2.391136},{"lat":48.976482,"lon":2.390159},{"lat":48.976482,"lon":2.390159},{"lat":48.974731,"lon":2.387668},{"lat":48.973709,"lon":2.386192},{"lat":48.972652,"lon":2.384605},{"lat":48.968609,"lon":2.378837},{"lat":48.96822,"lon":2.378295},{"lat":48.966747,"lon":2.376185},{"lat":48.966324,"lon":2.375595},{"lat":48.964603,"lon":2.373222},{"lat":48.963535,"lon":2.371701},{"lat":48.960766,"lon":2.367614},{"lat":48.958984,"lon":2.365061},{"lat":48.95578,"lon":2.360495},{"lat":48.954292,"lon":2.358332},{"lat":48.953278,"lon":2.356879},{"lat":48.952042,"lon":2.355177},{"lat":48.94706,"lon":2.348088},{"lat":48.946953,"lon":2.347953},{"lat":48.946728,"lon":2.34764},{"lat":48.946503,"lon":2.34735},{"lat":48.946304,"lon":2.347112},{"lat":48.946129,"lon":2.346914},{"lat":48.94582,"lon":2.346586},{"lat":48.945469,"lon":2.346257},{"lat":48.945171,"lon":2.345995},{"lat":48.944946,"lon":2.345809},{"lat":48.944435,"lon":2.34544},{"lat":48.944225,"lon":2.345304},{"lat":48.943874,"lon":2.345096},{"lat":48.943501,"lon":2.344906},{"lat":48.943245,"lon":2.344793},{"lat":48.942993,"lon":2.344696},{"lat":48.942772,"lon":2.344624},{"lat":48.942528,"lon":2.344552},{"lat":48.942238,"lon":2.344482},{"lat":48.941952,"lon":2.344429},{"lat":48.94157,"lon":2.344379},{"lat":48.941311,"lon":2.344355},{"lat":48.940922,"lon":2.344346},{"lat":48.94059,"lon":2.344357},{"lat":48.940121,"lon":2.344406},{"lat":48.939896,"lon":2.344441},{"lat":48.939583,"lon":2.344506},{"lat":48.939213,"lon":2.344599},{"lat":48.9352,"lon":2.345626},{"lat":48.9352,"lon":2.345626},{"lat":48.93325,"lon":2.346112},{"lat":48.931507,"lon":2.346505},{"lat":48.929214,"lon":2.347086},{"lat":48.927704,"lon":2.347472},{"lat":48.926018,"lon":2.347955},{"lat":48.924965,"lon":2.34824},{"lat":48.923576,"lon":2.348593},{"lat":48.923058,"lon":2.348701},{"lat":48.92178,"lon":2.349025},{"lat":48.921478,"lon":2.349134},{"lat":48.921093,"lon":2.349295},{"lat":48.920795,"lon":2.349436},{"lat":48.920532,"lon":2.349571},{"lat":48.92001,"lon":2.349867},{"lat":48.919548,"lon":2.350115},{"lat":48.919353,"lon":2.350208},{"lat":48.919094,"lon":2.350317},{"lat":48.918858,"lon":2.350404},{"lat":48.918556,"lon":2.350495},{"lat":48.91766,"lon":2.350713},{"lat":48.91721,"lon":2.350819},{"lat":48.917076,"lon":2.350843},{"lat":48.916786,"lon":2.350878},{"lat":48.916481,"lon":2.350898},{"lat":48.915825,"lon":2.350914},{"lat":48.915543,"lon":2.35094},{"lat":48.915367,"lon":2.350966},{"lat":48.915039,"lon":2.351038},{"lat":48.914745,"lon":2.351117},{"lat":48.914608,"lon":2.351158},{"lat":48.914074,"lon":2.35135},{"lat":48.913441,"lon":2.351601},{"lat":48.913284,"lon":2.351657},{"lat":48.912899,"lon":2.351779},{"lat":48.912476,"lon":2.351894},{"lat":48.91217,"lon":2.351999},{"lat":48.911934,"lon":2.352102},{"lat":48.911705,"lon":2.352225},{"lat":48.911343,"lon":2.352445},{"lat":48.911079,"lon":2.352637},{"lat":48.910679,"lon":2.352879},{"lat":48.910515,"lon":2.352963},{"lat":48.910286,"lon":2.353063},{"lat":48.910141,"lon":2.353117},{"lat":48.909988,"lon":2.353161},{"lat":48.909782,"lon":2.353209},{"lat":48.909458,"lon":2.353248},{"lat":48.909233,"lon":2.35325},{"lat":48.908966,"lon":2.353229},{"lat":48.90863,"lon":2.353168},{"lat":48.90797,"lon":2.35302},{"lat":48.9076,"lon":2.352981},{"lat":48.907322,"lon":2.352976},{"lat":48.906891,"lon":2.353016},{"lat":48.905937,"lon":2.353146},{"lat":48.905495,"lon":2.353237},{"lat":48.90366,"lon":2.353717},{"lat":48.902534,"lon":2.353953},{"lat":48.902279,"lon":2.35399},{"lat":48.901642,"lon":2.354119},{"lat":48.901283,"lon":2.354194},{"lat":48.900906,"lon":2.354287},{"lat":48.899971,"lon":2.354482},{"lat":48.899727,"lon":2.354521},{"lat":48.899296,"lon":2.354558},{"lat":48.897942,"lon":2.35463},{"lat":48.897636,"lon":2.354664},{"lat":48.897182,"lon":2.354736},{"lat":48.896698,"lon":2.354849},{"lat":48.896347,"lon":2.35495},{"lat":48.894997,"lon":2.355413},{"lat":48.894356,"lon":2.355673},{"lat":48.891533,"lon":2.357025},{"lat":48.891209,"lon":2.357172},{"lat":48.890877,"lon":2.357307},{"lat":48.890579,"lon":2.357415},{"lat":48.89032,"lon":2.35749},{"lat":48.890076,"lon":2.357548},{"lat":48.889816,"lon":2.357594},{"lat":48.888329,"lon":2.357822},{"lat":48.887524,"lon":2.357891},{"lat":48.886402,"lon":2.357972},{"lat":48.884312,"lon":2.357993},{"lat":48.883568,"lon":2.358015},{"lat":48.883125,"lon":2.357999},{"lat":48.882969,"lon":2.357986},{"lat":48.882751,"lon":2.357955},{"lat":48.882294,"lon":2.357846},{"lat":48.882133,"lon":2.357795},{"lat":48.881969,"lon":2.357732},{"lat":48.881393,"lon":2.357473}]},"entrances":[{"id":"IDFM:StopPlaceEntrance:50171258","parentStopId":"IDFM:69254","name":"r. Pasteur","lat":49.031878590627535,"lon":2.69870109506934},{"id":"IDFM:StopPlaceEntrance:50171259","parentStopId":"IDFM:69254","name":"r. Pasteur","lat":49.03215777857545,"lon":2.6988772503328002},{"id":"IDFM:StopPlaceEntrance:50171260","parentStopId":"IDFM:69254","name":"r. Pasteur","lat":49.03239214487842,"lon":2.6991083676657244},{"id":"IDFM:StopPlaceEntrance:50147778","parentStopId":"IDFM:71410","name":"r. de Saint-Quentin","code":"2","lat":48.87959674225429,"lon":2.3560724185048474},{"id":"IDFM:StopPlaceEntrance:50170864","parentStopId":"IDFM:71410","name":"r. de Maubeuge","code":"9","lat":48.88212519851938,"lon":2.354650283454813},{"id":"IDFM:StopPlaceEntrance:50170424","parentStopId":"IDFM:71410","name":"Esplanade Napoléon III","code":"5","lat":48.88006704377754,"lon":2.3548939548712315},{"id":"IDFM:StopPlaceEntrance:50170276","parentStopId":"IDFM:71410","name":"Cour des Taxis","code":"7","lat":48.88052973898862,"lon":2.353974640075389},{"id":"IDFM:StopPlaceEntrance:50147781","parentStopId":"IDFM:71410","name":"r. de Dunkerque","code":"3","lat":48.87969768098524,"lon":2.354775811992991},{"id":"IDFM:StopPlaceEntrance:50147780","parentStopId":"IDFM:71410","name":"bd de Denain","code":"4","lat":48.879758424819464,"lon":2.3543659983381993},{"id":"IDFM:StopPlaceEntrance:50147779","parentStopId":"IDFM:71410","name":"r. du Fbg Saint-Denis","code":"1","lat":48.87939408721905,"lon":2.3568521346592783},{"id":"IDFM:StopPlaceEntrance:50170405","parentStopId":"IDFM:69065","name":"Entrée / Sortie","lat":48.97556812853208,"lon":2.6422422047496896},{"id":"IDFM:StopPlaceEntrance:50170406","parentStopId":"IDFM:69065","name":"Entrée / Sortie","lat":48.975712817166354,"lon":2.642514413361084},{"id":"IDFM:StopPlaceEntrance:50229026","parentStopId":"IDFM:411397","name":"Parking","lat":49.231225804773096,"lon":2.887365244878781},{"id":"IDFM:StopPlaceEntrance:50229027","parentStopId":"IDFM:411397","name":"Parking Sud","lat":49.23056952425343,"lon":2.8873529469253705},{"id":"IDFM:StopPlaceEntrance:50229025","parentStopId":"IDFM:411397","name":"Place de la Gare","lat":49.231224955011385,"lon":2.8864592261545754},{"id":"IDFM:StopPlaceEntrance:50229033","parentStopId":"IDFM:411391","name":"Avenue de la gare","lat":49.14272771408749,"lon":2.7945750303626817},{"id":"IDFM:StopPlaceEntrance:50229034","parentStopId":"IDFM:411391","name":"Parking","lat":49.14246628006823,"lon":2.7941649441714516},{"id":"IDFM:StopPlaceEntrance:50229046","parentStopId":"IDFM:411406","name":"Entrée / Sortie","lat":49.09546371102945,"lon":2.7439524296035316},{"id":"IDFM:StopPlaceEntrance:50229047","parentStopId":"IDFM:411406","name":"Entrée / Sortie","lat":49.09622071353028,"lon":2.7447702055062226},{"id":"IDFM:StopPlaceEntrance:50229044","parentStopId":"IDFM:411406","name":"Avenue de la Gare","lat":49.09585222203614,"lon":2.744840478277471},{"id":"IDFM:StopPlaceEntrance:50229045","parentStopId":"IDFM:411406","name":"Entrée / Sortie","lat":49.09536518730644,"lon":2.7441309078509453}]}